{
    "g_basis_dervs": {
        "1": [
            [
                "(0)*k[0] - (0)*k[1] - (0)*k[2] - 1.0",
                "(0)*k[0] - (0)*k[1] - (0)*k[2] - 1.0",
                "(0)*k[0] - (0)*k[1] - (0)*k[2] - 1.0"
            ],
            [
                "(0)*k[0] + (0)*k[1] + (0)*k[2] + 1.0",
                "(0)*k[0] - (0)*k[1] + (0)*k[2] - (0)",
                "(0)*k[0] - (0)*k[1] + (0)*k[2] - (0)"
            ],
            [
                "0",
                "(0)*k[0] + (0)*k[1] + (0)*k[2] + 1.0",
                "(0)*k[0] - (0)*k[1] - (0)*k[2] + (0)"
            ],
            [
                "0",
                "0",
                "(0)*k[0] + (0)*k[1] - (0)*k[2] + 1.0"
            ]
        ]
    },
    "sdim": 10,
    "s_basis_dervs": {
        "3": [
            "(0)*c[0]*k[0]*k[0] - (0)*c[0]*k[0]*k[1] - (0)*c[0]*k[0]*k[2] + (0)*c[0]*k[0] + (0)*c[0]*k[1]*k[1] + (0)*c[0]*k[1]*k[2] - (0)*c[0]*k[1] - (0)*c[0]*k[2]*k[2] + (0)*c[0]*k[2] - (0)*c[0] + (0)*c[1]*k[0]*k[0] - (0)*c[1]*k[0]*k[1] - (0)*c[1]*k[0]*k[2] + (0)*c[1]*k[0] - (0)*c[1]*k[1]*k[1] + (0)*c[1]*k[1]*k[2] - (0)*c[1]*k[1] + (0)*c[1]*k[2]*k[2] + (0)*c[1]*k[2] - (0)*c[1] + (0)*c[2]*k[0]*k[0] - (0)*c[2]*k[0]*k[1] + (0)*c[2]*k[0]*k[2] - (0)*c[2]*k[0] - (0)*c[2]*k[1]*k[1] - (0)*c[2]*k[1]*k[2] + (0)*c[2]*k[1] + (0)*c[2]*k[2]*k[2] - (0)*c[2]*k[2] + (0)*c[2] + (0)*c[3]*k[0]*k[0] - (0)*c[3]*k[0]*k[1] + (0)*c[3]*k[0]*k[2] - (0)*c[3]*k[0] - (0)*c[3]*k[1]*k[1] - (0)*c[3]*k[1]*k[2] + (0)*c[3]*k[1] + (0)*c[3]*k[2]*k[2] - (0)*c[3]*k[2] + (0)*c[3] - (0)*c[4]*k[0]*k[0] + (0)*c[4]*k[0]*k[1] - (0)*c[4]*k[0]*k[2] + (0)*c[4]*k[0] + (0)*c[4]*k[1]*k[1] + (0)*c[4]*k[1]*k[2] - (0)*c[4]*k[1] - (0)*c[4]*k[2]*k[2] + (0)*c[4]*k[2] - (0)*c[4] + (0)*c[5]*k[0]*k[0] - (0)*c[5]*k[0]*k[1] + (0)*c[5]*k[0]*k[2] - (0)*c[5]*k[0] - (0)*c[5]*k[1]*k[1] - (0)*c[5]*k[1]*k[2] + (0)*c[5]*k[1] + (0)*c[5]*k[2]*k[2] - (0)*c[5]*k[2] + (0)*c[5] + (0)*c[6]*k[0]*k[0] - (0)*c[6]*k[0]*k[1] + (0)*c[6]*k[0]*k[2] - (0)*c[6]*k[0] - (0)*c[6]*k[1]*k[1] - (0)*c[6]*k[1]*k[2] + (0)*c[6]*k[1] + (0)*c[6]*k[2]*k[2] - (0)*c[6]*k[2] + (0)*c[6] - (0)*c[7]*k[0]*k[0] + (0)*c[7]*k[0]*k[1] - (0)*c[7]*k[0]*k[2] + (0)*c[7]*k[0] + (0)*c[7]*k[1]*k[1] + (0)*c[7]*k[1]*k[2] - (0)*c[7]*k[1] - (0)*c[7]*k[2]*k[2] + (0)*c[7]*k[2] - (0)*c[7] - (0)*c[8]*k[0]*k[0] + (0)*c[8]*k[0]*k[1] - (0)*c[8]*k[0]*k[2] + (0)*c[8]*k[0] + (0)*c[8]*k[1]*k[1] + (0)*c[8]*k[1]*k[2] - (0)*c[8]*k[1] - (0)*c[8]*k[2]*k[2] + (0)*c[8]*k[2] - (0)*c[8] + (0)*c[9]*k[0]*k[0] + (0)*c[9]*k[0]*k[1] + (0)*c[9]*k[0]*k[2] - (0)*c[9]*k[0] + (0)*c[9]*k[1]*k[1] - (0)*c[9]*k[1]*k[2] + (0)*c[9]*k[1] - (0)*c[9]*k[2]*k[2] - (0)*c[9]*k[2] + (0)*c[9]",
            "(0)*c[0]*k[0]*k[0] + (0)*c[0]*k[0]*k[1] + (0)*c[0]*k[0]*k[2] - (0)*c[0]*k[0] + (0)*c[0]*k[1]*k[1] + (0)*c[0]*k[1]*k[2] - (0)*c[0]*k[1] + (0)*c[0]*k[2]*k[2] - (0)*c[0]*k[2] + (0)*c[0] - (0)*c[1]*k[0]*k[0] + (0)*c[1]*k[0]*k[1] + (0)*c[1]*k[0]*k[2] - (0)*c[1]*k[0] + (0)*c[1]*k[1]*k[1] + (0)*c[1]*k[1]*k[2] - (0)*c[1]*k[1] + (0)*c[1]*k[2]*k[2] - (0)*c[1]*k[2] + (0)*c[1] - (0)*c[2]*k[0]*k[0] + (0)*c[2]*k[0]*k[1] - (0)*c[2]*k[0]*k[2] + (0)*c[2]*k[0] + (0)*c[2]*k[1]*k[1] + (0)*c[2]*k[1]*k[2] - (0)*c[2]*k[1] + (0)*c[2]*k[2]*k[2] - (0)*c[2]*k[2] - (0)*c[2] - (0)*c[3]*k[0]*k[0] + (0)*c[3]*k[0]*k[1] - (0)*c[3]*k[0]*k[2] + (0)*c[3]*k[0] + (0)*c[3]*k[1]*k[1] + (0)*c[3]*k[1]*k[2] - (0)*c[3]*k[1] + (0)*c[3]*k[2]*k[2] - (0)*c[3]*k[2] - (0)*c[3] + (0)*c[4]*k[0]*k[0] - (0)*c[4]*k[0]*k[1] + (0)*c[4]*k[0]*k[2] - (0)*c[4]*k[0] - (0)*c[4]*k[1]*k[1] - (0)*c[4]*k[1]*k[2] + (0)*c[4]*k[1] - (0)*c[4]*k[2]*k[2] + (0)*c[4]*k[2] + (0)*c[4] - (0)*c[5]*k[0]*k[0] + (0)*c[5]*k[0]*k[1] - (0)*c[5]*k[0]*k[2] + (0)*c[5]*k[0] + (0)*c[5]*k[1]*k[1] + (0)*c[5]*k[1]*k[2] - (0)*c[5]*k[1] + (0)*c[5]*k[2]*k[2] - (0)*c[5]*k[2] - (0)*c[5] - (0)*c[6]*k[0]*k[0] + (0)*c[6]*k[0]*k[1] - (0)*c[6]*k[0]*k[2] + (0)*c[6]*k[0] + (0)*c[6]*k[1]*k[1] + (0)*c[6]*k[1]*k[2] - (0)*c[6]*k[1] + (0)*c[6]*k[2]*k[2] - (0)*c[6]*k[2] - (0)*c[6] + (0)*c[7]*k[0]*k[0] - (0)*c[7]*k[0]*k[1] + (0)*c[7]*k[0]*k[2] - (0)*c[7]*k[0] - (0)*c[7]*k[1]*k[1] - (0)*c[7]*k[1]*k[2] + (0)*c[7]*k[1] - (0)*c[7]*k[2]*k[2] + (0)*c[7]*k[2] + (0)*c[7] + (0)*c[8]*k[0]*k[0] - (0)*c[8]*k[0]*k[1] + (0)*c[8]*k[0]*k[2] - (0)*c[8]*k[0] - (0)*c[8]*k[1]*k[1] - (0)*c[8]*k[1]*k[2] + (0)*c[8]*k[1] - (0)*c[8]*k[2]*k[2] + (0)*c[8]*k[2] + (0)*c[8] + (0)*c[9]*k[0]*k[0] - (0)*c[9]*k[0]*k[1] - (0)*c[9]*k[0]*k[2] + (0)*c[9]*k[0] - (0)*c[9]*k[1]*k[1] - (0)*c[9]*k[1]*k[2] + (0)*c[9]*k[1] - (0)*c[9]*k[2]*k[2] + (0)*c[9]*k[2] - (0)*c[9]",
            "(0)*c[0]*k[0]*k[0] + (0)*c[0]*k[0]*k[1] - (0)*c[0]*k[0]*k[2] + (0)*c[0]*k[0] + (0)*c[0]*k[1]*k[1] + (0)*c[0]*k[1]*k[2] - (0)*c[0]*k[1] + (0)*c[0]*k[2]*k[2] + (0)*c[0]*k[2] - (0)*c[0] + (0)*c[1]*k[0]*k[0] + (0)*c[1]*k[0]*k[1] - (0)*c[1]*k[0]*k[2] + (0)*c[1]*k[0] + (0)*c[1]*k[1]*k[1] + (0)*c[1]*k[1]*k[2] - (0)*c[1]*k[1] + (0)*c[1]*k[2]*k[2] + (0)*c[1]*k[2] - (0)*c[1] + (0)*c[2]*k[0]*k[0] - (0)*c[2]*k[0]*k[1] + (0)*c[2]*k[0]*k[2] - (0)*c[2]*k[0] - (0)*c[2]*k[1]*k[1] - (0)*c[2]*k[1]*k[2] + (0)*c[2]*k[1] - (0)*c[2]*k[2]*k[2] + (0)*c[2]*k[2] + (0)*c[2] + (0)*c[3]*k[0]*k[0] - (0)*c[3]*k[0]*k[1] + (0)*c[3]*k[0]*k[2] + (0)*c[3]*k[0] - (0)*c[3]*k[1]*k[1] - (0)*c[3]*k[1]*k[2] + (0)*c[3]*k[1] - (0)*c[3]*k[2]*k[2] + (0)*c[3]*k[2] + (0)*c[3] - (0)*c[4]*k[0]*k[0] + (0)*c[4]*k[0]*k[1] - (0)*c[4]*k[0]*k[2] - (0)*c[4]*k[0] + (0)*c[4]*k[1]*k[1] + (0)*c[4]*k[1]*k[2] - (0)*c[4]*k[1] + (0)*c[4]*k[2]*k[2] - (0)*c[4]*k[2] - (0)*c[4] + (0)*c[5]*k[0]*k[0] - (0)*c[5]*k[0]*k[1] + (0)*c[5]*k[0]*k[2] + (0)*c[5]*k[0] - (0)*c[5]*k[1]*k[1] - (0)*c[5]*k[1]*k[2] + (0)*c[5]*k[1] - (0)*c[5]*k[2]*k[2] + (0)*c[5]*k[2] + (0)*c[5] + (0)*c[6]*k[0]*k[0] - (0)*c[6]*k[0]*k[1] + (0)*c[6]*k[0]*k[2] - (0)*c[6]*k[0] - (0)*c[6]*k[1]*k[1] - (0)*c[6]*k[1]*k[2] + (0)*c[6]*k[1] - (0)*c[6]*k[2]*k[2] + (0)*c[6]*k[2] + (0)*c[6] - (0)*c[7]*k[0]*k[0] + (0)*c[7]*k[0]*k[1] - (0)*c[7]*k[0]*k[2] - (0)*c[7]*k[0] + (0)*c[7]*k[1]*k[1] + (0)*c[7]*k[1]*k[2] - (0)*c[7]*k[1] + (0)*c[7]*k[2]*k[2] - (0)*c[7]*k[2] - (0)*c[7] - (0)*c[8]*k[0]*k[0] + (0)*c[8]*k[0]*k[1] - (0)*c[8]*k[0]*k[2] + (0)*c[8]*k[0] + (0)*c[8]*k[1]*k[1] + (0)*c[8]*k[1]*k[2] - (0)*c[8]*k[1] + (0)*c[8]*k[2]*k[2] - (0)*c[8]*k[2] - (0)*c[8] - (0)*c[9]*k[0]*k[0] - (0)*c[9]*k[0]*k[1] + (0)*c[9]*k[0]*k[2] - (0)*c[9]*k[0] - (0)*c[9]*k[1]*k[1] - (0)*c[9]*k[1]*k[2] + (0)*c[9]*k[1] - (0)*c[9]*k[2]*k[2] - (0)*c[9]*k[2] + (0)*c[9]",
            "(0)*c[0]*k[0]*k[0] + (0)*c[0]*k[0]*k[1] + (0)*c[0]*k[0]*k[2] - (0)*c[0]*k[0] + (0)*c[0]*k[1]*k[1] + (0)*c[0]*k[1]*k[2] - (0)*c[0]*k[1] + (0)*c[0]*k[2]*k[2] - (0)*c[0]*k[2] + (0)*c[0] - (0)*c[1]*k[0]*k[0] + (0)*c[1]*k[0]*k[1] + (0)*c[1]*k[0]*k[2] - (0)*c[1]*k[0] + (0)*c[1]*k[1]*k[1] + (0)*c[1]*k[1]*k[2] - (0)*c[1]*k[1] + (0)*c[1]*k[2]*k[2] - (0)*c[1]*k[2] + (0)*c[1] - (0)*c[2]*k[0]*k[0] + (0)*c[2]*k[0]*k[1] - (0)*c[2]*k[0]*k[2] + (0)*c[2]*k[0] + (0)*c[2]*k[1]*k[1] + (0)*c[2]*k[1]*k[2] - (0)*c[2]*k[1] + (0)*c[2]*k[2]*k[2] - (0)*c[2]*k[2] - (0)*c[2] - (0)*c[3]*k[0]*k[0] + (0)*c[3]*k[0]*k[1] - (0)*c[3]*k[0]*k[2] + (0)*c[3]*k[0] + (0)*c[3]*k[1]*k[1] + (0)*c[3]*k[1]*k[2] - (0)*c[3]*k[1] + (0)*c[3]*k[2]*k[2] - (0)*c[3]*k[2] - (0)*c[3] + (0)*c[4]*k[0]*k[0] - (0)*c[4]*k[0]*k[1] + (0)*c[4]*k[0]*k[2] - (0)*c[4]*k[0] - (0)*c[4]*k[1]*k[1] - (0)*c[4]*k[1]*k[2] + (0)*c[4]*k[1] - (0)*c[4]*k[2]*k[2] + (0)*c[4]*k[2] + (0)*c[4] - (0)*c[5]*k[0]*k[0] + (0)*c[5]*k[0]*k[1] - (0)*c[5]*k[0]*k[2] + (0)*c[5]*k[0] + (0)*c[5]*k[1]*k[1] + (0)*c[5]*k[1]*k[2] - (0)*c[5]*k[1] + (0)*c[5]*k[2]*k[2] - (0)*c[5]*k[2] - (0)*c[5] - (0)*c[6]*k[0]*k[0] + (0)*c[6]*k[0]*k[1] - (0)*c[6]*k[0]*k[2] + (0)*c[6]*k[0] + (0)*c[6]*k[1]*k[1] + (0)*c[6]*k[1]*k[2] - (0)*c[6]*k[1] + (0)*c[6]*k[2]*k[2] - (0)*c[6]*k[2] - (0)*c[6] + (0)*c[7]*k[0]*k[0] - (0)*c[7]*k[0]*k[1] + (0)*c[7]*k[0]*k[2] - (0)*c[7]*k[0] - (0)*c[7]*k[1]*k[1] - (0)*c[7]*k[1]*k[2] + (0)*c[7]*k[1] - (0)*c[7]*k[2]*k[2] + (0)*c[7]*k[2] + (0)*c[7] + (0)*c[8]*k[0]*k[0] - (0)*c[8]*k[0]*k[1] + (0)*c[8]*k[0]*k[2] - (0)*c[8]*k[0] - (0)*c[8]*k[1]*k[1] - (0)*c[8]*k[1]*k[2] + (0)*c[8]*k[1] - (0)*c[8]*k[2]*k[2] + (0)*c[8]*k[2] + (0)*c[8] + (0)*c[9]*k[0]*k[0] - (0)*c[9]*k[0]*k[1] - (0)*c[9]*k[0]*k[2] + (0)*c[9]*k[0] - (0)*c[9]*k[1]*k[1] - (0)*c[9]*k[1]*k[2] + (0)*c[9]*k[1] - (0)*c[9]*k[2]*k[2] + (0)*c[9]*k[2] - (0)*c[9]",
            "(0)*c[0]*k[0]*k[0] - (0)*c[0]*k[0]*k[1] + (0)*c[0]*k[0]*k[2] - (0)*c[0]*k[0] + (0)*c[0]*k[1]*k[1] - (0)*c[0]*k[1]*k[2] - (0)*c[0]*k[1] - (0)*c[0]*k[2]*k[2] - (0)*c[0]*k[2] + (0)*c[0] - (0)*c[1]*k[0]*k[0] - (0)*c[1]*k[0]*k[1] - (0)*c[1]*k[0]*k[2] + (0)*c[1]*k[0] - (0)*c[1]*k[1]*k[1] + (0)*c[1]*k[1]*k[2] - (0)*c[1]*k[1] - (0)*c[1]*k[2]*k[2] + (0)*c[1]*k[2] - (0)*c[1] + (0)*c[2]*k[0]*k[0] + (0)*c[2]*k[0]*k[1] + (0)*c[2]*k[0]*k[2] - (0)*c[2]*k[0] + (0)*c[2]*k[1]*k[1] + (0)*c[2]*k[1]*k[2] - (0)*c[2]*k[1] - (0)*c[2]*k[2]*k[2] - (0)*c[2]*k[2] + (0)*c[2] - (0)*c[3]*k[0]*k[0] + (0)*c[3]*k[0]*k[1] - (0)*c[3]*k[0]*k[2] + (0)*c[3]*k[0] + (0)*c[3]*k[1]*k[1] + (0)*c[3]*k[1]*k[2] + (0)*c[3]*k[1] + (0)*c[3]*k[2]*k[2] + (0)*c[3]*k[2] - (0)*c[3] + (0)*c[4]*k[0]*k[0] - (0)*c[4]*k[0]*k[1] + (0)*c[4]*k[0]*k[2] - (0)*c[4]*k[0] - (0)*c[4]*k[1]*k[1] - (0)*c[4]*k[1]*k[2] - (0)*c[4]*k[1] - (0)*c[4]*k[2]*k[2] - (0)*c[4]*k[2] + (0)*c[4] - (0)*c[5]*k[0]*k[0] + (0)*c[5]*k[0]*k[1] - (0)*c[5]*k[0]*k[2] + (0)*c[5]*k[0] + (0)*c[5]*k[1]*k[1] + (0)*c[5]*k[1]*k[2] - (0)*c[5]*k[1] + (0)*c[5]*k[2]*k[2] - (0)*c[5]*k[2] - (0)*c[5] + (0)*c[6]*k[0]*k[0] + (0)*c[6]*k[0]*k[1] + (0)*c[6]*k[0]*k[2] - (0)*c[6]*k[0] + (0)*c[6]*k[1]*k[1] + (0)*c[6]*k[1]*k[2] - (0)*c[6]*k[1] - (0)*c[6]*k[2]*k[2] - (0)*c[6]*k[2] + (0)*c[6] + (0)*c[7]*k[0]*k[0] - (0)*c[7]*k[0]*k[1] + (0)*c[7]*k[0]*k[2] - (0)*c[7]*k[0] - (0)*c[7]*k[1]*k[1] - (0)*c[7]*k[1]*k[2] + (0)*c[7]*k[1] - (0)*c[7]*k[2]*k[2] + (0)*c[7]*k[2] + (0)*c[7] - (0)*c[8]*k[0]*k[0] - (0)*c[8]*k[0]*k[1] - (0)*c[8]*k[0]*k[2] + (0)*c[8]*k[0] - (0)*c[8]*k[1]*k[1] - (0)*c[8]*k[1]*k[2] + (0)*c[8]*k[1] + (0)*c[8]*k[2]*k[2] + (0)*c[8]*k[2] - (0)*c[8] - (0)*c[9]*k[0]*k[0] + (0)*c[9]*k[0]*k[1] - (0)*c[9]*k[0]*k[2] + (0)*c[9]*k[0] - (0)*c[9]*k[1]*k[1] + (0)*c[9]*k[1]*k[2] + (0)*c[9]*k[1] + (0)*c[9]*k[2]*k[2] + (0)*c[9]*k[2] - (0)*c[9]",
            "(0)*c[0]*k[0]*k[0] + (0)*c[0]*k[0]*k[1] - (0)*c[0]*k[0]*k[2] + (0)*c[0]*k[0] + (0)*c[0]*k[1]*k[1] + (0)*c[0]*k[1]*k[2] - (0)*c[0]*k[1] + (0)*c[0]*k[2]*k[2] + (0)*c[0]*k[2] - (0)*c[0] + (0)*c[1]*k[0]*k[0] + (0)*c[1]*k[0]*k[1] - (0)*c[1]*k[0]*k[2] + (0)*c[1]*k[0] + (0)*c[1]*k[1]*k[1] + (0)*c[1]*k[1]*k[2] + (0)*c[1]*k[1] - (0)*c[1]*k[2]*k[2] + (0)*c[1]*k[2] - (0)*c[1] - (0)*c[2]*k[0]*k[0] - (0)*c[2]*k[0]*k[1] - (0)*c[2]*k[0]*k[2] + (0)*c[2]*k[0] + (0)*c[2]*k[1]*k[1] - (0)*c[2]*k[1]*k[2] - (0)*c[2]*k[1] - (0)*c[2]*k[2]*k[2] - (0)*c[2]*k[2] + (0)*c[2] - (0)*c[3]*k[0]*k[0] + (0)*c[3]*k[0]*k[1] - (0)*c[3]*k[0]*k[2] - (0)*c[3]*k[0] - (0)*c[3]*k[1]*k[1] - (0)*c[3]*k[1]*k[2] + (0)*c[3]*k[1] - (0)*c[3]*k[2]*k[2] + (0)*c[3]*k[2] - (0)*c[3] + (0)*c[4]*k[0]*k[0] - (0)*c[4]*k[0]*k[1] + (0)*c[4]*k[0]*k[2] + (0)*c[4]*k[0] + (0)*c[4]*k[1]*k[1] + (0)*c[4]*k[1]*k[2] - (0)*c[4]*k[1] + (0)*c[4]*k[2]*k[2] - (0)*c[4]*k[2] + (0)*c[4] - (0)*c[5]*k[0]*k[0] + (0)*c[5]*k[0]*k[1] - (0)*c[5]*k[0]*k[2] + (0)*c[5]*k[0] - (0)*c[5]*k[1]*k[1] - (0)*c[5]*k[1]*k[2] + (0)*c[5]*k[1] - (0)*c[5]*k[2]*k[2] + (0)*c[5]*k[2] - (0)*c[5] - (0)*c[6]*k[0]*k[0] - (0)*c[6]*k[0]*k[1] - (0)*c[6]*k[0]*k[2] + (0)*c[6]*k[0] + (0)*c[6]*k[1]*k[1] - (0)*c[6]*k[1]*k[2] - (0)*c[6]*k[1] - (0)*c[6]*k[2]*k[2] - (0)*c[6]*k[2] + (0)*c[6] + (0)*c[7]*k[0]*k[0] - (0)*c[7]*k[0]*k[1] + (0)*c[7]*k[0]*k[2] - (0)*c[7]*k[0] + (0)*c[7]*k[1]*k[1] + (0)*c[7]*k[1]*k[2] - (0)*c[7]*k[1] + (0)*c[7]*k[2]*k[2] - (0)*c[7]*k[2] + (0)*c[7] + (0)*c[8]*k[0]*k[0] + (0)*c[8]*k[0]*k[1] + (0)*c[8]*k[0]*k[2] - (0)*c[8]*k[0] - (0)*c[8]*k[1]*k[1] + (0)*c[8]*k[1]*k[2] + (0)*c[8]*k[1] + (0)*c[8]*k[2]*k[2] + (0)*c[8]*k[2] - (0)*c[8] - (0)*c[9]*k[0]*k[0] - (0)*c[9]*k[0]*k[1] + (0)*c[9]*k[0]*k[2] - (0)*c[9]*k[0] - (0)*c[9]*k[1]*k[1] - (0)*c[9]*k[1]*k[2] + (0)*c[9]*k[1] + (0)*c[9]*k[2]*k[2] - (0)*c[9]*k[2] + (0)*c[9]",
            "(0)*c[0]*k[0]*k[0] + (0)*c[0]*k[0]*k[1] - (0)*c[0]*k[0]*k[2] + (0)*c[0]*k[0] + (0)*c[0]*k[1]*k[1] + (0)*c[0]*k[1]*k[2] - (0)*c[0]*k[1] + (0)*c[0]*k[2]*k[2] + (0)*c[0]*k[2] - (0)*c[0] + (0)*c[1]*k[0]*k[0] + (0)*c[1]*k[0]*k[1] - (0)*c[1]*k[0]*k[2] + (0)*c[1]*k[0] + (0)*c[1]*k[1]*k[1] + (0)*c[1]*k[1]*k[2] - (0)*c[1]*k[1] + (0)*c[1]*k[2]*k[2] + (0)*c[1]*k[2] - (0)*c[1] + (0)*c[2]*k[0]*k[0] - (0)*c[2]*k[0]*k[1] + (0)*c[2]*k[0]*k[2] - (0)*c[2]*k[0] - (0)*c[2]*k[1]*k[1] - (0)*c[2]*k[1]*k[2] + (0)*c[2]*k[1] - (0)*c[2]*k[2]*k[2] + (0)*c[2]*k[2] + (0)*c[2] + (0)*c[3]*k[0]*k[0] - (0)*c[3]*k[0]*k[1] + (0)*c[3]*k[0]*k[2] + (0)*c[3]*k[0] - (0)*c[3]*k[1]*k[1] - (0)*c[3]*k[1]*k[2] + (0)*c[3]*k[1] - (0)*c[3]*k[2]*k[2] + (0)*c[3]*k[2] + (0)*c[3] - (0)*c[4]*k[0]*k[0] + (0)*c[4]*k[0]*k[1] - (0)*c[4]*k[0]*k[2] - (0)*c[4]*k[0] + (0)*c[4]*k[1]*k[1] + (0)*c[4]*k[1]*k[2] - (0)*c[4]*k[1] + (0)*c[4]*k[2]*k[2] - (0)*c[4]*k[2] - (0)*c[4] + (0)*c[5]*k[0]*k[0] - (0)*c[5]*k[0]*k[1] + (0)*c[5]*k[0]*k[2] + (0)*c[5]*k[0] - (0)*c[5]*k[1]*k[1] - (0)*c[5]*k[1]*k[2] + (0)*c[5]*k[1] - (0)*c[5]*k[2]*k[2] + (0)*c[5]*k[2] + (0)*c[5] + (0)*c[6]*k[0]*k[0] - (0)*c[6]*k[0]*k[1] + (0)*c[6]*k[0]*k[2] - (0)*c[6]*k[0] - (0)*c[6]*k[1]*k[1] - (0)*c[6]*k[1]*k[2] + (0)*c[6]*k[1] - (0)*c[6]*k[2]*k[2] + (0)*c[6]*k[2] + (0)*c[6] - (0)*c[7]*k[0]*k[0] + (0)*c[7]*k[0]*k[1] - (0)*c[7]*k[0]*k[2] - (0)*c[7]*k[0] + (0)*c[7]*k[1]*k[1] + (0)*c[7]*k[1]*k[2] - (0)*c[7]*k[1] + (0)*c[7]*k[2]*k[2] - (0)*c[7]*k[2] - (0)*c[7] - (0)*c[8]*k[0]*k[0] + (0)*c[8]*k[0]*k[1] - (0)*c[8]*k[0]*k[2] + (0)*c[8]*k[0] + (0)*c[8]*k[1]*k[1] + (0)*c[8]*k[1]*k[2] - (0)*c[8]*k[1] + (0)*c[8]*k[2]*k[2] - (0)*c[8]*k[2] - (0)*c[8] - (0)*c[9]*k[0]*k[0] - (0)*c[9]*k[0]*k[1] + (0)*c[9]*k[0]*k[2] - (0)*c[9]*k[0] - (0)*c[9]*k[1]*k[1] - (0)*c[9]*k[1]*k[2] + (0)*c[9]*k[1] - (0)*c[9]*k[2]*k[2] - (0)*c[9]*k[2] + (0)*c[9]",
            "(0)*c[0]*k[0]*k[0] + (0)*c[0]*k[0]*k[1] - (0)*c[0]*k[0]*k[2] + (0)*c[0]*k[0] + (0)*c[0]*k[1]*k[1] + (0)*c[0]*k[1]*k[2] - (0)*c[0]*k[1] + (0)*c[0]*k[2]*k[2] + (0)*c[0]*k[2] - (0)*c[0] + (0)*c[1]*k[0]*k[0] + (0)*c[1]*k[0]*k[1] - (0)*c[1]*k[0]*k[2] + (0)*c[1]*k[0] + (0)*c[1]*k[1]*k[1] + (0)*c[1]*k[1]*k[2] + (0)*c[1]*k[1] - (0)*c[1]*k[2]*k[2] + (0)*c[1]*k[2] - (0)*c[1] - (0)*c[2]*k[0]*k[0] - (0)*c[2]*k[0]*k[1] - (0)*c[2]*k[0]*k[2] + (0)*c[2]*k[0] + (0)*c[2]*k[1]*k[1] - (0)*c[2]*k[1]*k[2] - (0)*c[2]*k[1] - (0)*c[2]*k[2]*k[2] - (0)*c[2]*k[2] + (0)*c[2] - (0)*c[3]*k[0]*k[0] + (0)*c[3]*k[0]*k[1] - (0)*c[3]*k[0]*k[2] - (0)*c[3]*k[0] - (0)*c[3]*k[1]*k[1] - (0)*c[3]*k[1]*k[2] + (0)*c[3]*k[1] - (0)*c[3]*k[2]*k[2] + (0)*c[3]*k[2] - (0)*c[3] + (0)*c[4]*k[0]*k[0] - (0)*c[4]*k[0]*k[1] + (0)*c[4]*k[0]*k[2] + (0)*c[4]*k[0] + (0)*c[4]*k[1]*k[1] + (0)*c[4]*k[1]*k[2] - (0)*c[4]*k[1] + (0)*c[4]*k[2]*k[2] - (0)*c[4]*k[2] + (0)*c[4] - (0)*c[5]*k[0]*k[0] + (0)*c[5]*k[0]*k[1] - (0)*c[5]*k[0]*k[2] + (0)*c[5]*k[0] - (0)*c[5]*k[1]*k[1] - (0)*c[5]*k[1]*k[2] + (0)*c[5]*k[1] - (0)*c[5]*k[2]*k[2] + (0)*c[5]*k[2] - (0)*c[5] - (0)*c[6]*k[0]*k[0] - (0)*c[6]*k[0]*k[1] - (0)*c[6]*k[0]*k[2] + (0)*c[6]*k[0] + (0)*c[6]*k[1]*k[1] - (0)*c[6]*k[1]*k[2] - (0)*c[6]*k[1] - (0)*c[6]*k[2]*k[2] - (0)*c[6]*k[2] + (0)*c[6] + (0)*c[7]*k[0]*k[0] - (0)*c[7]*k[0]*k[1] + (0)*c[7]*k[0]*k[2] - (0)*c[7]*k[0] + (0)*c[7]*k[1]*k[1] + (0)*c[7]*k[1]*k[2] - (0)*c[7]*k[1] + (0)*c[7]*k[2]*k[2] - (0)*c[7]*k[2] + (0)*c[7] + (0)*c[8]*k[0]*k[0] + (0)*c[8]*k[0]*k[1] + (0)*c[8]*k[0]*k[2] - (0)*c[8]*k[0] - (0)*c[8]*k[1]*k[1] + (0)*c[8]*k[1]*k[2] + (0)*c[8]*k[1] + (0)*c[8]*k[2]*k[2] + (0)*c[8]*k[2] - (0)*c[8] - (0)*c[9]*k[0]*k[0] - (0)*c[9]*k[0]*k[1] + (0)*c[9]*k[0]*k[2] - (0)*c[9]*k[0] - (0)*c[9]*k[1]*k[1] - (0)*c[9]*k[1]*k[2] + (0)*c[9]*k[1] + (0)*c[9]*k[2]*k[2] - (0)*c[9]*k[2] + (0)*c[9]",
            "(0)*c[0]*k[0]*k[0] + (0)*c[0]*k[0]*k[1] - (0)*c[0]*k[0]*k[2] + (0)*c[0]*k[0] + (0)*c[0]*k[1]*k[1] + (0)*c[0]*k[1]*k[2] - (0)*c[0]*k[1] + (0)*c[0]*k[2]*k[2] + (0)*c[0]*k[2] - (0)*c[0] + (0)*c[1]*k[0]*k[0] + (0)*c[1]*k[0]*k[1] - (0)*c[1]*k[0]*k[2] + (0)*c[1]*k[0] + (0)*c[1]*k[1]*k[1] + (0)*c[1]*k[1]*k[2] + (0)*c[1]*k[1] - (0)*c[1]*k[2]*k[2] + (0)*c[1]*k[2] - (0)*c[1] + (0)*c[2]*k[0]*k[0] - (0)*c[2]*k[0]*k[1] + (0)*c[2]*k[0]*k[2] - (0)*c[2]*k[0] - (0)*c[2]*k[1]*k[1] - (0)*c[2]*k[1]*k[2] + (0)*c[2]*k[1] - (0)*c[2]*k[2]*k[2] + (0)*c[2]*k[2] + (0)*c[2] - (0)*c[3]*k[0]*k[0] - (0)*c[3]*k[0]*k[1] + (0)*c[3]*k[0]*k[2] - (0)*c[3]*k[0] - (0)*c[3]*k[1]*k[1] - (0)*c[3]*k[1]*k[2] - (0)*c[3]*k[1] - (0)*c[3]*k[2]*k[2] - (0)*c[3]*k[2] + (0)*c[3] + (0)*c[4]*k[0]*k[0] + (0)*c[4]*k[0]*k[1] - (0)*c[4]*k[0]*k[2] + (0)*c[4]*k[0] + (0)*c[4]*k[1]*k[1] + (0)*c[4]*k[1]*k[2] + (0)*c[4]*k[1] + (0)*c[4]*k[2]*k[2] + (0)*c[4]*k[2] - (0)*c[4] - (0)*c[5]*k[0]*k[0] - (0)*c[5]*k[0]*k[1] + (0)*c[5]*k[0]*k[2] - (0)*c[5]*k[0] - (0)*c[5]*k[1]*k[1] - (0)*c[5]*k[1]*k[2] - (0)*c[5]*k[1] - (0)*c[5]*k[2]*k[2] - (0)*c[5]*k[2] + (0)*c[5] + (0)*c[6]*k[0]*k[0] - (0)*c[6]*k[0]*k[1] + (0)*c[6]*k[0]*k[2] - (0)*c[6]*k[0] - (0)*c[6]*k[1]*k[1] - (0)*c[6]*k[1]*k[2] + (0)*c[6]*k[1] - (0)*c[6]*k[2]*k[2] + (0)*c[6]*k[2] + (0)*c[6] + (0)*c[7]*k[0]*k[0] + (0)*c[7]*k[0]*k[1] - (0)*c[7]*k[0]*k[2] + (0)*c[7]*k[0] + (0)*c[7]*k[1]*k[1] + (0)*c[7]*k[1]*k[2] + (0)*c[7]*k[1] + (0)*c[7]*k[2]*k[2] + (0)*c[7]*k[2] - (0)*c[7] - (0)*c[8]*k[0]*k[0] + (0)*c[8]*k[0]*k[1] - (0)*c[8]*k[0]*k[2] + (0)*c[8]*k[0] + (0)*c[8]*k[1]*k[1] + (0)*c[8]*k[1]*k[2] - (0)*c[8]*k[1] + (0)*c[8]*k[2]*k[2] - (0)*c[8]*k[2] - (0)*c[8] - (0)*c[9]*k[0]*k[0] - (0)*c[9]*k[0]*k[1] + (0)*c[9]*k[0]*k[2] - (0)*c[9]*k[0] - (0)*c[9]*k[1]*k[1] - (0)*c[9]*k[1]*k[2] + (0)*c[9]*k[1] - (0)*c[9]*k[2]*k[2] - (0)*c[9]*k[2] + (0)*c[9]",
            "(0)*c[0]*k[0]*k[0] + (0)*c[0]*k[0]*k[1] + (0)*c[0]*k[0]*k[2] - (0)*c[0]*k[0] + (0)*c[0]*k[1]*k[1] + (0)*c[0]*k[1]*k[2] - (0)*c[0]*k[1] + (0)*c[0]*k[2]*k[2] - (0)*c[0]*k[2] + (0)*c[0] - (0)*c[1]*k[0]*k[0] + (0)*c[1]*k[0]*k[1] + (0)*c[1]*k[0]*k[2] - (0)*c[1]*k[0] + (0)*c[1]*k[1]*k[1] + (0)*c[1]*k[1]*k[2] - (0)*c[1]*k[1] + (0)*c[1]*k[2]*k[2] - (0)*c[1]*k[2] + (0)*c[1] - (0)*c[2]*k[0]*k[0] + (0)*c[2]*k[0]*k[1] - (0)*c[2]*k[0]*k[2] + (0)*c[2]*k[0] + (0)*c[2]*k[1]*k[1] + (0)*c[2]*k[1]*k[2] - (0)*c[2]*k[1] + (0)*c[2]*k[2]*k[2] - (0)*c[2]*k[2] - (0)*c[2] - (0)*c[3]*k[0]*k[0] + (0)*c[3]*k[0]*k[1] - (0)*c[3]*k[0]*k[2] + (0)*c[3]*k[0] + (0)*c[3]*k[1]*k[1] + (0)*c[3]*k[1]*k[2] - (0)*c[3]*k[1] + (0)*c[3]*k[2]*k[2] - (0)*c[3]*k[2] - (0)*c[3] + (0)*c[4]*k[0]*k[0] - (0)*c[4]*k[0]*k[1] + (0)*c[4]*k[0]*k[2] - (0)*c[4]*k[0] - (0)*c[4]*k[1]*k[1] - (0)*c[4]*k[1]*k[2] + (0)*c[4]*k[1] - (0)*c[4]*k[2]*k[2] + (0)*c[4]*k[2] + (0)*c[4] - (0)*c[5]*k[0]*k[0] + (0)*c[5]*k[0]*k[1] - (0)*c[5]*k[0]*k[2] + (0)*c[5]*k[0] + (0)*c[5]*k[1]*k[1] + (0)*c[5]*k[1]*k[2] - (0)*c[5]*k[1] + (0)*c[5]*k[2]*k[2] - (0)*c[5]*k[2] - (0)*c[5] - (0)*c[6]*k[0]*k[0] + (0)*c[6]*k[0]*k[1] - (0)*c[6]*k[0]*k[2] + (0)*c[6]*k[0] + (0)*c[6]*k[1]*k[1] + (0)*c[6]*k[1]*k[2] - (0)*c[6]*k[1] + (0)*c[6]*k[2]*k[2] - (0)*c[6]*k[2] - (0)*c[6] + (0)*c[7]*k[0]*k[0] - (0)*c[7]*k[0]*k[1] + (0)*c[7]*k[0]*k[2] - (0)*c[7]*k[0] - (0)*c[7]*k[1]*k[1] - (0)*c[7]*k[1]*k[2] + (0)*c[7]*k[1] - (0)*c[7]*k[2]*k[2] + (0)*c[7]*k[2] + (0)*c[7] + (0)*c[8]*k[0]*k[0] - (0)*c[8]*k[0]*k[1] + (0)*c[8]*k[0]*k[2] - (0)*c[8]*k[0] - (0)*c[8]*k[1]*k[1] - (0)*c[8]*k[1]*k[2] + (0)*c[8]*k[1] - (0)*c[8]*k[2]*k[2] + (0)*c[8]*k[2] + (0)*c[8] + (0)*c[9]*k[0]*k[0] - (0)*c[9]*k[0]*k[1] - (0)*c[9]*k[0]*k[2] + (0)*c[9]*k[0] - (0)*c[9]*k[1]*k[1] - (0)*c[9]*k[1]*k[2] + (0)*c[9]*k[1] - (0)*c[9]*k[2]*k[2] + (0)*c[9]*k[2] - (0)*c[9]",
            "(0)*c[0]*k[0]*k[0] - (0)*c[0]*k[0]*k[1] + (0)*c[0]*k[0]*k[2] - (0)*c[0]*k[0] + (0)*c[0]*k[1]*k[1] - (0)*c[0]*k[1]*k[2] - (0)*c[0]*k[1] - (0)*c[0]*k[2]*k[2] - (0)*c[0]*k[2] + (0)*c[0] - (0)*c[1]*k[0]*k[0] - (0)*c[1]*k[0]*k[1] - (0)*c[1]*k[0]*k[2] + (0)*c[1]*k[0] - (0)*c[1]*k[1]*k[1] + (0)*c[1]*k[1]*k[2] - (0)*c[1]*k[1] - (0)*c[1]*k[2]*k[2] + (0)*c[1]*k[2] - (0)*c[1] + (0)*c[2]*k[0]*k[0] + (0)*c[2]*k[0]*k[1] + (0)*c[2]*k[0]*k[2] - (0)*c[2]*k[0] + (0)*c[2]*k[1]*k[1] + (0)*c[2]*k[1]*k[2] - (0)*c[2]*k[1] - (0)*c[2]*k[2]*k[2] - (0)*c[2]*k[2] + (0)*c[2] - (0)*c[3]*k[0]*k[0] + (0)*c[3]*k[0]*k[1] - (0)*c[3]*k[0]*k[2] + (0)*c[3]*k[0] + (0)*c[3]*k[1]*k[1] + (0)*c[3]*k[1]*k[2] + (0)*c[3]*k[1] + (0)*c[3]*k[2]*k[2] + (0)*c[3]*k[2] - (0)*c[3] + (0)*c[4]*k[0]*k[0] - (0)*c[4]*k[0]*k[1] + (0)*c[4]*k[0]*k[2] - (0)*c[4]*k[0] - (0)*c[4]*k[1]*k[1] - (0)*c[4]*k[1]*k[2] - (0)*c[4]*k[1] - (0)*c[4]*k[2]*k[2] - (0)*c[4]*k[2] + (0)*c[4] - (0)*c[5]*k[0]*k[0] + (0)*c[5]*k[0]*k[1] - (0)*c[5]*k[0]*k[2] + (0)*c[5]*k[0] + (0)*c[5]*k[1]*k[1] + (0)*c[5]*k[1]*k[2] - (0)*c[5]*k[1] + (0)*c[5]*k[2]*k[2] - (0)*c[5]*k[2] - (0)*c[5] + (0)*c[6]*k[0]*k[0] + (0)*c[6]*k[0]*k[1] + (0)*c[6]*k[0]*k[2] - (0)*c[6]*k[0] + (0)*c[6]*k[1]*k[1] + (0)*c[6]*k[1]*k[2] - (0)*c[6]*k[1] - (0)*c[6]*k[2]*k[2] - (0)*c[6]*k[2] + (0)*c[6] + (0)*c[7]*k[0]*k[0] - (0)*c[7]*k[0]*k[1] + (0)*c[7]*k[0]*k[2] - (0)*c[7]*k[0] - (0)*c[7]*k[1]*k[1] - (0)*c[7]*k[1]*k[2] + (0)*c[7]*k[1] - (0)*c[7]*k[2]*k[2] + (0)*c[7]*k[2] + (0)*c[7] - (0)*c[8]*k[0]*k[0] - (0)*c[8]*k[0]*k[1] - (0)*c[8]*k[0]*k[2] + (0)*c[8]*k[0] - (0)*c[8]*k[1]*k[1] - (0)*c[8]*k[1]*k[2] + (0)*c[8]*k[1] + (0)*c[8]*k[2]*k[2] + (0)*c[8]*k[2] - (0)*c[8] - (0)*c[9]*k[0]*k[0] + (0)*c[9]*k[0]*k[1] - (0)*c[9]*k[0]*k[2] + (0)*c[9]*k[0] - (0)*c[9]*k[1]*k[1] + (0)*c[9]*k[1]*k[2] + (0)*c[9]*k[1] + (0)*c[9]*k[2]*k[2] + (0)*c[9]*k[2] - (0)*c[9]",
            "(0)*c[0]*k[0]*k[0] + (0)*c[0]*k[0]*k[1] - (0)*c[0]*k[0]*k[2] + (0)*c[0]*k[0] + (0)*c[0]*k[1]*k[1] + (0)*c[0]*k[1]*k[2] - (0)*c[0]*k[1] + (0)*c[0]*k[2]*k[2] + (0)*c[0]*k[2] - (0)*c[0] + (0)*c[1]*k[0]*k[0] + (0)*c[1]*k[0]*k[1] - (0)*c[1]*k[0]*k[2] + (0)*c[1]*k[0] + (0)*c[1]*k[1]*k[1] + (0)*c[1]*k[1]*k[2] + (0)*c[1]*k[1] - (0)*c[1]*k[2]*k[2] + (0)*c[1]*k[2] - (0)*c[1] - (0)*c[2]*k[0]*k[0] - (0)*c[2]*k[0]*k[1] - (0)*c[2]*k[0]*k[2] + (0)*c[2]*k[0] + (0)*c[2]*k[1]*k[1] - (0)*c[2]*k[1]*k[2] - (0)*c[2]*k[1] - (0)*c[2]*k[2]*k[2] - (0)*c[2]*k[2] + (0)*c[2] - (0)*c[3]*k[0]*k[0] + (0)*c[3]*k[0]*k[1] - (0)*c[3]*k[0]*k[2] - (0)*c[3]*k[0] - (0)*c[3]*k[1]*k[1] - (0)*c[3]*k[1]*k[2] + (0)*c[3]*k[1] - (0)*c[3]*k[2]*k[2] + (0)*c[3]*k[2] - (0)*c[3] + (0)*c[4]*k[0]*k[0] - (0)*c[4]*k[0]*k[1] + (0)*c[4]*k[0]*k[2] + (0)*c[4]*k[0] + (0)*c[4]*k[1]*k[1] + (0)*c[4]*k[1]*k[2] - (0)*c[4]*k[1] + (0)*c[4]*k[2]*k[2] - (0)*c[4]*k[2] + (0)*c[4] - (0)*c[5]*k[0]*k[0] + (0)*c[5]*k[0]*k[1] - (0)*c[5]*k[0]*k[2] + (0)*c[5]*k[0] - (0)*c[5]*k[1]*k[1] - (0)*c[5]*k[1]*k[2] + (0)*c[5]*k[1] - (0)*c[5]*k[2]*k[2] + (0)*c[5]*k[2] - (0)*c[5] - (0)*c[6]*k[0]*k[0] - (0)*c[6]*k[0]*k[1] - (0)*c[6]*k[0]*k[2] + (0)*c[6]*k[0] + (0)*c[6]*k[1]*k[1] - (0)*c[6]*k[1]*k[2] - (0)*c[6]*k[1] - (0)*c[6]*k[2]*k[2] - (0)*c[6]*k[2] + (0)*c[6] + (0)*c[7]*k[0]*k[0] - (0)*c[7]*k[0]*k[1] + (0)*c[7]*k[0]*k[2] - (0)*c[7]*k[0] + (0)*c[7]*k[1]*k[1] + (0)*c[7]*k[1]*k[2] - (0)*c[7]*k[1] + (0)*c[7]*k[2]*k[2] - (0)*c[7]*k[2] + (0)*c[7] + (0)*c[8]*k[0]*k[0] + (0)*c[8]*k[0]*k[1] + (0)*c[8]*k[0]*k[2] - (0)*c[8]*k[0] - (0)*c[8]*k[1]*k[1] + (0)*c[8]*k[1]*k[2] + (0)*c[8]*k[1] + (0)*c[8]*k[2]*k[2] + (0)*c[8]*k[2] - (0)*c[8] - (0)*c[9]*k[0]*k[0] - (0)*c[9]*k[0]*k[1] + (0)*c[9]*k[0]*k[2] - (0)*c[9]*k[0] - (0)*c[9]*k[1]*k[1] - (0)*c[9]*k[1]*k[2] + (0)*c[9]*k[1] + (0)*c[9]*k[2]*k[2] - (0)*c[9]*k[2] + (0)*c[9]",
            "(0)*c[0]*k[0]*k[0] - (0)*c[0]*k[0]*k[1] + (0)*c[0]*k[0]*k[2] - (0)*c[0]*k[0] + (0)*c[0]*k[1]*k[1] - (0)*c[0]*k[1]*k[2] - (0)*c[0]*k[1] - (0)*c[0]*k[2]*k[2] - (0)*c[0]*k[2] + (0)*c[0] - (0)*c[1]*k[0]*k[0] - (0)*c[1]*k[0]*k[1] - (0)*c[1]*k[0]*k[2] + (0)*c[1]*k[0] - (0)*c[1]*k[1]*k[1] + (0)*c[1]*k[1]*k[2] - (0)*c[1]*k[1] - (0)*c[1]*k[2]*k[2] + (0)*c[1]*k[2] - (0)*c[1] + (0)*c[2]*k[0]*k[0] + (0)*c[2]*k[0]*k[1] + (0)*c[2]*k[0]*k[2] - (0)*c[2]*k[0] + (0)*c[2]*k[1]*k[1] + (0)*c[2]*k[1]*k[2] - (0)*c[2]*k[1] - (0)*c[2]*k[2]*k[2] - (0)*c[2]*k[2] + (0)*c[2] - (0)*c[3]*k[0]*k[0] + (0)*c[3]*k[0]*k[1] - (0)*c[3]*k[0]*k[2] + (0)*c[3]*k[0] + (0)*c[3]*k[1]*k[1] + (0)*c[3]*k[1]*k[2] + (0)*c[3]*k[1] + (0)*c[3]*k[2]*k[2] + (0)*c[3]*k[2] - (0)*c[3] + (0)*c[4]*k[0]*k[0] - (0)*c[4]*k[0]*k[1] + (0)*c[4]*k[0]*k[2] - (0)*c[4]*k[0] - (0)*c[4]*k[1]*k[1] - (0)*c[4]*k[1]*k[2] - (0)*c[4]*k[1] - (0)*c[4]*k[2]*k[2] - (0)*c[4]*k[2] + (0)*c[4] - (0)*c[5]*k[0]*k[0] + (0)*c[5]*k[0]*k[1] - (0)*c[5]*k[0]*k[2] + (0)*c[5]*k[0] + (0)*c[5]*k[1]*k[1] + (0)*c[5]*k[1]*k[2] - (0)*c[5]*k[1] + (0)*c[5]*k[2]*k[2] - (0)*c[5]*k[2] - (0)*c[5] + (0)*c[6]*k[0]*k[0] + (0)*c[6]*k[0]*k[1] + (0)*c[6]*k[0]*k[2] - (0)*c[6]*k[0] + (0)*c[6]*k[1]*k[1] + (0)*c[6]*k[1]*k[2] - (0)*c[6]*k[1] - (0)*c[6]*k[2]*k[2] - (0)*c[6]*k[2] + (0)*c[6] + (0)*c[7]*k[0]*k[0] - (0)*c[7]*k[0]*k[1] + (0)*c[7]*k[0]*k[2] - (0)*c[7]*k[0] - (0)*c[7]*k[1]*k[1] - (0)*c[7]*k[1]*k[2] + (0)*c[7]*k[1] - (0)*c[7]*k[2]*k[2] + (0)*c[7]*k[2] + (0)*c[7] - (0)*c[8]*k[0]*k[0] - (0)*c[8]*k[0]*k[1] - (0)*c[8]*k[0]*k[2] + (0)*c[8]*k[0] - (0)*c[8]*k[1]*k[1] - (0)*c[8]*k[1]*k[2] + (0)*c[8]*k[1] + (0)*c[8]*k[2]*k[2] + (0)*c[8]*k[2] - (0)*c[8] - (0)*c[9]*k[0]*k[0] + (0)*c[9]*k[0]*k[1] - (0)*c[9]*k[0]*k[2] + (0)*c[9]*k[0] - (0)*c[9]*k[1]*k[1] + (0)*c[9]*k[1]*k[2] + (0)*c[9]*k[1] + (0)*c[9]*k[2]*k[2] + (0)*c[9]*k[2] - (0)*c[9]",
            "(0)*c[0]*k[0]*k[0] - (0)*c[0]*k[0]*k[1] + (0)*c[0]*k[0]*k[2] - (0)*c[0]*k[0] - (0)*c[0]*k[1]*k[1] - (0)*c[0]*k[1]*k[2] - (0)*c[0]*k[1] - (0)*c[0]*k[2]*k[2] - (0)*c[0]*k[2] + (0)*c[0] + (0)*c[1]*k[0]*k[0] - (0)*c[1]*k[0]*k[1] + (0)*c[1]*k[0]*k[2] + (0)*c[1]*k[0] - (0)*c[1]*k[1]*k[1] - (0)*c[1]*k[1]*k[2] + (0)*c[1]*k[1] - (0)*c[1]*k[2]*k[2] + (0)*c[1]*k[2] + (0)*c[1] + (0)*c[2]*k[0]*k[0] + (0)*c[2]*k[0]*k[1] + (0)*c[2]*k[0]*k[2] - (0)*c[2]*k[0] + (0)*c[2]*k[1]*k[1] - (0)*c[2]*k[1]*k[2] - (0)*c[2]*k[1] - (0)*c[2]*k[2]*k[2] - (0)*c[2]*k[2] + (0)*c[2] + (0)*c[3]*k[0]*k[0] + (0)*c[3]*k[0]*k[1] + (0)*c[3]*k[0]*k[2] - (0)*c[3]*k[0] - (0)*c[3]*k[1]*k[1] + (0)*c[3]*k[1]*k[2] + (0)*c[3]*k[1] + (0)*c[3]*k[2]*k[2] - (0)*c[3]*k[2] + (0)*c[3] - (0)*c[4]*k[0]*k[0] + (0)*c[4]*k[0]*k[1] - (0)*c[4]*k[0]*k[2] + (0)*c[4]*k[0] + (0)*c[4]*k[1]*k[1] + (0)*c[4]*k[1]*k[2] - (0)*c[4]*k[1] - (0)*c[4]*k[2]*k[2] + (0)*c[4]*k[2] - (0)*c[4] - (0)*c[5]*k[0]*k[0] + (0)*c[5]*k[0]*k[1] - (0)*c[5]*k[0]*k[2] - (0)*c[5]*k[0] + (0)*c[5]*k[1]*k[1] + (0)*c[5]*k[1]*k[2] - (0)*c[5]*k[1] + (0)*c[5]*k[2]*k[2] - (0)*c[5]*k[2] - (0)*c[5] - (0)*c[6]*k[0]*k[0] + (0)*c[6]*k[0]*k[1] - (0)*c[6]*k[0]*k[2] + (0)*c[6]*k[0] + (0)*c[6]*k[1]*k[1] + (0)*c[6]*k[1]*k[2] - (0)*c[6]*k[1] - (0)*c[6]*k[2]*k[2] + (0)*c[6]*k[2] - (0)*c[6] + (0)*c[7]*k[0]*k[0] - (0)*c[7]*k[0]*k[1] + (0)*c[7]*k[0]*k[2] - (0)*c[7]*k[0] - (0)*c[7]*k[1]*k[1] - (0)*c[7]*k[1]*k[2] + (0)*c[7]*k[1] + (0)*c[7]*k[2]*k[2] - (0)*c[7]*k[2] + (0)*c[7] - (0)*c[8]*k[0]*k[0] - (0)*c[8]*k[0]*k[1] - (0)*c[8]*k[0]*k[2] + (0)*c[8]*k[0] - (0)*c[8]*k[1]*k[1] + (0)*c[8]*k[1]*k[2] + (0)*c[8]*k[1] + (0)*c[8]*k[2]*k[2] + (0)*c[8]*k[2] - (0)*c[8] + (0)*c[9]*k[0]*k[0] + (0)*c[9]*k[0]*k[1] + (0)*c[9]*k[0]*k[2] - (0)*c[9]*k[0] - (0)*c[9]*k[1]*k[1] + (0)*c[9]*k[1]*k[2] + (0)*c[9]*k[1] + (0)*c[9]*k[2]*k[2] - (0)*c[9]*k[2] + (0)*c[9]",
            "(0)*c[0]*k[0]*k[0] - (0)*c[0]*k[0]*k[1] - (0)*c[0]*k[0]*k[2] + (0)*c[0]*k[0] + (0)*c[0]*k[1]*k[1] + (0)*c[0]*k[1]*k[2] - (0)*c[0]*k[1] - (0)*c[0]*k[2]*k[2] + (0)*c[0]*k[2] - (0)*c[0] + (0)*c[1]*k[0]*k[0] - (0)*c[1]*k[0]*k[1] + (0)*c[1]*k[0]*k[2] - (0)*c[1]*k[0] - (0)*c[1]*k[1]*k[1] + (0)*c[1]*k[1]*k[2] + (0)*c[1]*k[1] + (0)*c[1]*k[2]*k[2] - (0)*c[1]*k[2] + (0)*c[1] - (0)*c[2]*k[0]*k[0] - (0)*c[2]*k[0]*k[1] - (0)*c[2]*k[0]*k[2] + (0)*c[2]*k[0] + (0)*c[2]*k[1]*k[1] + (0)*c[2]*k[1]*k[2] - (0)*c[2]*k[1] + (0)*c[2]*k[2]*k[2] - (0)*c[2]*k[2] + (0)*c[2] + (0)*c[3]*k[0]*k[0] - (0)*c[3]*k[0]*k[1] + (0)*c[3]*k[0]*k[2] - (0)*c[3]*k[0] - (0)*c[3]*k[1]*k[1] - (0)*c[3]*k[1]*k[2] - (0)*c[3]*k[1] + (0)*c[3]*k[2]*k[2] - (0)*c[3]*k[2] + (0)*c[3] - (0)*c[4]*k[0]*k[0] + (0)*c[4]*k[0]*k[1] - (0)*c[4]*k[0]*k[2] + (0)*c[4]*k[0] + (0)*c[4]*k[1]*k[1] + (0)*c[4]*k[1]*k[2] - (0)*c[4]*k[1] - (0)*c[4]*k[2]*k[2] + (0)*c[4]*k[2] - (0)*c[4] + (0)*c[5]*k[0]*k[0] - (0)*c[5]*k[0]*k[1] + (0)*c[5]*k[0]*k[2] - (0)*c[5]*k[0] - (0)*c[5]*k[1]*k[1] - (0)*c[5]*k[1]*k[2] + (0)*c[5]*k[1] + (0)*c[5]*k[2]*k[2] + (0)*c[5]*k[2] + (0)*c[5] - (0)*c[6]*k[0]*k[0] + (0)*c[6]*k[0]*k[1] - (0)*c[6]*k[0]*k[2] + (0)*c[6]*k[0] + (0)*c[6]*k[1]*k[1] + (0)*c[6]*k[1]*k[2] + (0)*c[6]*k[1] - (0)*c[6]*k[2]*k[2] + (0)*c[6]*k[2] - (0)*c[6] + (0)*c[7]*k[0]*k[0] - (0)*c[7]*k[0]*k[1] + (0)*c[7]*k[0]*k[2] - (0)*c[7]*k[0] - (0)*c[7]*k[1]*k[1] - (0)*c[7]*k[1]*k[2] + (0)*c[7]*k[1] + (0)*c[7]*k[2]*k[2] - (0)*c[7]*k[2] + (0)*c[7] + (0)*c[8]*k[0]*k[0] + (0)*c[8]*k[0]*k[1] + (0)*c[8]*k[0]*k[2] - (0)*c[8]*k[0] - (0)*c[8]*k[1]*k[1] + (0)*c[8]*k[1]*k[2] + (0)*c[8]*k[1] - (0)*c[8]*k[2]*k[2] + (0)*c[8]*k[2] - (0)*c[8] + (0)*c[9]*k[0]*k[0] - (0)*c[9]*k[0]*k[1] + (0)*c[9]*k[0]*k[2] - (0)*c[9]*k[0] - (0)*c[9]*k[1]*k[1] - (0)*c[9]*k[1]*k[2] - (0)*c[9]*k[1] + (0)*c[9]*k[2]*k[2] - (0)*c[9]*k[2] + (0)*c[9]",
            "(0)*c[0]*k[0]*k[0] + (0)*c[0]*k[0]*k[1] - (0)*c[0]*k[0]*k[2] + (0)*c[0]*k[0] + (0)*c[0]*k[1]*k[1] + (0)*c[0]*k[1]*k[2] - (0)*c[0]*k[1] + (0)*c[0]*k[2]*k[2] + (0)*c[0]*k[2] - (0)*c[0] + (0)*c[1]*k[0]*k[0] + (0)*c[1]*k[0]*k[1] - (0)*c[1]*k[0]*k[2] + (0)*c[1]*k[0] + (0)*c[1]*k[1]*k[1] + (0)*c[1]*k[1]*k[2] + (0)*c[1]*k[1] - (0)*c[1]*k[2]*k[2] + (0)*c[1]*k[2] - (0)*c[1] - (0)*c[2]*k[0]*k[0] - (0)*c[2]*k[0]*k[1] - (0)*c[2]*k[0]*k[2] + (0)*c[2]*k[0] + (0)*c[2]*k[1]*k[1] - (0)*c[2]*k[1]*k[2] - (0)*c[2]*k[1] - (0)*c[2]*k[2]*k[2] - (0)*c[2]*k[2] + (0)*c[2] - (0)*c[3]*k[0]*k[0] + (0)*c[3]*k[0]*k[1] - (0)*c[3]*k[0]*k[2] - (0)*c[3]*k[0] - (0)*c[3]*k[1]*k[1] - (0)*c[3]*k[1]*k[2] + (0)*c[3]*k[1] - (0)*c[3]*k[2]*k[2] + (0)*c[3]*k[2] - (0)*c[3] + (0)*c[4]*k[0]*k[0] - (0)*c[4]*k[0]*k[1] + (0)*c[4]*k[0]*k[2] + (0)*c[4]*k[0] + (0)*c[4]*k[1]*k[1] + (0)*c[4]*k[1]*k[2] - (0)*c[4]*k[1] + (0)*c[4]*k[2]*k[2] - (0)*c[4]*k[2] + (0)*c[4] - (0)*c[5]*k[0]*k[0] + (0)*c[5]*k[0]*k[1] - (0)*c[5]*k[0]*k[2] + (0)*c[5]*k[0] - (0)*c[5]*k[1]*k[1] - (0)*c[5]*k[1]*k[2] + (0)*c[5]*k[1] - (0)*c[5]*k[2]*k[2] + (0)*c[5]*k[2] - (0)*c[5] - (0)*c[6]*k[0]*k[0] - (0)*c[6]*k[0]*k[1] - (0)*c[6]*k[0]*k[2] + (0)*c[6]*k[0] + (0)*c[6]*k[1]*k[1] - (0)*c[6]*k[1]*k[2] - (0)*c[6]*k[1] - (0)*c[6]*k[2]*k[2] - (0)*c[6]*k[2] + (0)*c[6] + (0)*c[7]*k[0]*k[0] - (0)*c[7]*k[0]*k[1] + (0)*c[7]*k[0]*k[2] - (0)*c[7]*k[0] + (0)*c[7]*k[1]*k[1] + (0)*c[7]*k[1]*k[2] - (0)*c[7]*k[1] + (0)*c[7]*k[2]*k[2] - (0)*c[7]*k[2] + (0)*c[7] + (0)*c[8]*k[0]*k[0] + (0)*c[8]*k[0]*k[1] + (0)*c[8]*k[0]*k[2] - (0)*c[8]*k[0] - (0)*c[8]*k[1]*k[1] + (0)*c[8]*k[1]*k[2] + (0)*c[8]*k[1] + (0)*c[8]*k[2]*k[2] + (0)*c[8]*k[2] - (0)*c[8] - (0)*c[9]*k[0]*k[0] - (0)*c[9]*k[0]*k[1] + (0)*c[9]*k[0]*k[2] - (0)*c[9]*k[0] - (0)*c[9]*k[1]*k[1] - (0)*c[9]*k[1]*k[2] + (0)*c[9]*k[1] + (0)*c[9]*k[2]*k[2] - (0)*c[9]*k[2] + (0)*c[9]",
            "(0)*c[0]*k[0]*k[0] - (0)*c[0]*k[0]*k[1] - (0)*c[0]*k[0]*k[2] + (0)*c[0]*k[0] + (0)*c[0]*k[1]*k[1] + (0)*c[0]*k[1]*k[2] - (0)*c[0]*k[1] - (0)*c[0]*k[2]*k[2] + (0)*c[0]*k[2] - (0)*c[0] + (0)*c[1]*k[0]*k[0] - (0)*c[1]*k[0]*k[1] + (0)*c[1]*k[0]*k[2] - (0)*c[1]*k[0] - (0)*c[1]*k[1]*k[1] + (0)*c[1]*k[1]*k[2] + (0)*c[1]*k[1] + (0)*c[1]*k[2]*k[2] - (0)*c[1]*k[2] + (0)*c[1] - (0)*c[2]*k[0]*k[0] - (0)*c[2]*k[0]*k[1] - (0)*c[2]*k[0]*k[2] + (0)*c[2]*k[0] + (0)*c[2]*k[1]*k[1] + (0)*c[2]*k[1]*k[2] - (0)*c[2]*k[1] + (0)*c[2]*k[2]*k[2] - (0)*c[2]*k[2] + (0)*c[2] + (0)*c[3]*k[0]*k[0] - (0)*c[3]*k[0]*k[1] + (0)*c[3]*k[0]*k[2] - (0)*c[3]*k[0] - (0)*c[3]*k[1]*k[1] - (0)*c[3]*k[1]*k[2] - (0)*c[3]*k[1] + (0)*c[3]*k[2]*k[2] - (0)*c[3]*k[2] + (0)*c[3] - (0)*c[4]*k[0]*k[0] + (0)*c[4]*k[0]*k[1] - (0)*c[4]*k[0]*k[2] + (0)*c[4]*k[0] + (0)*c[4]*k[1]*k[1] + (0)*c[4]*k[1]*k[2] - (0)*c[4]*k[1] - (0)*c[4]*k[2]*k[2] + (0)*c[4]*k[2] - (0)*c[4] + (0)*c[5]*k[0]*k[0] - (0)*c[5]*k[0]*k[1] + (0)*c[5]*k[0]*k[2] - (0)*c[5]*k[0] - (0)*c[5]*k[1]*k[1] - (0)*c[5]*k[1]*k[2] + (0)*c[5]*k[1] + (0)*c[5]*k[2]*k[2] + (0)*c[5]*k[2] + (0)*c[5] - (0)*c[6]*k[0]*k[0] + (0)*c[6]*k[0]*k[1] - (0)*c[6]*k[0]*k[2] + (0)*c[6]*k[0] + (0)*c[6]*k[1]*k[1] + (0)*c[6]*k[1]*k[2] + (0)*c[6]*k[1] - (0)*c[6]*k[2]*k[2] + (0)*c[6]*k[2] - (0)*c[6] + (0)*c[7]*k[0]*k[0] - (0)*c[7]*k[0]*k[1] + (0)*c[7]*k[0]*k[2] - (0)*c[7]*k[0] - (0)*c[7]*k[1]*k[1] - (0)*c[7]*k[1]*k[2] + (0)*c[7]*k[1] + (0)*c[7]*k[2]*k[2] - (0)*c[7]*k[2] + (0)*c[7] + (0)*c[8]*k[0]*k[0] + (0)*c[8]*k[0]*k[1] + (0)*c[8]*k[0]*k[2] - (0)*c[8]*k[0] - (0)*c[8]*k[1]*k[1] + (0)*c[8]*k[1]*k[2] + (0)*c[8]*k[1] - (0)*c[8]*k[2]*k[2] + (0)*c[8]*k[2] - (0)*c[8] + (0)*c[9]*k[0]*k[0] - (0)*c[9]*k[0]*k[1] + (0)*c[9]*k[0]*k[2] - (0)*c[9]*k[0] - (0)*c[9]*k[1]*k[1] - (0)*c[9]*k[1]*k[2] - (0)*c[9]*k[1] + (0)*c[9]*k[2]*k[2] - (0)*c[9]*k[2] + (0)*c[9]",
            "(0)*c[0]*k[0]*k[0] + (0)*c[0]*k[0]*k[1] - (0)*c[0]*k[0]*k[2] + (0)*c[0]*k[0] + (0)*c[0]*k[1]*k[1] + (0)*c[0]*k[1]*k[2] - (0)*c[0]*k[1] - (0)*c[0]*k[2]*k[2] + (0)*c[0]*k[2] - (0)*c[0] + (0)*c[1]*k[0]*k[0] - (0)*c[1]*k[0]*k[1] + (0)*c[1]*k[0]*k[2] - (0)*c[1]*k[0] - (0)*c[1]*k[1]*k[1] - (0)*c[1]*k[1]*k[2] + (0)*c[1]*k[1] - (0)*c[1]*k[2]*k[2] - (0)*c[1]*k[2] + (0)*c[1] + (0)*c[2]*k[0]*k[0] + (0)*c[2]*k[0]*k[1] + (0)*c[2]*k[0]*k[2] - (0)*c[2]*k[0] + (0)*c[2]*k[1]*k[1] + (0)*c[2]*k[1]*k[2] + (0)*c[2]*k[1] + (0)*c[2]*k[2]*k[2] + (0)*c[2]*k[2] - (0)*c[2] + (0)*c[3]*k[0]*k[0] - (0)*c[3]*k[0]*k[1] - (0)*c[3]*k[0]*k[2] + (0)*c[3]*k[0] - (0)*c[3]*k[1]*k[1] - (0)*c[3]*k[1]*k[2] + (0)*c[3]*k[1] - (0)*c[3]*k[2]*k[2] + (0)*c[3]*k[2] + (0)*c[3] - (0)*c[4]*k[0]*k[0] - (0)*c[4]*k[0]*k[1] + (0)*c[4]*k[0]*k[2] - (0)*c[4]*k[0] - (0)*c[4]*k[1]*k[1] - (0)*c[4]*k[1]*k[2] - (0)*c[4]*k[1] + (0)*c[4]*k[2]*k[2] - (0)*c[4]*k[2] + (0)*c[4] + (0)*c[5]*k[0]*k[0] - (0)*c[5]*k[0]*k[1] - (0)*c[5]*k[0]*k[2] + (0)*c[5]*k[0] - (0)*c[5]*k[1]*k[1] - (0)*c[5]*k[1]*k[2] + (0)*c[5]*k[1] - (0)*c[5]*k[2]*k[2] + (0)*c[5]*k[2] + (0)*c[5] + (0)*c[6]*k[0]*k[0] - (0)*c[6]*k[0]*k[1] - (0)*c[6]*k[0]*k[2] + (0)*c[6]*k[0] + (0)*c[6]*k[1]*k[1] - (0)*c[6]*k[1]*k[2] + (0)*c[6]*k[1] - (0)*c[6]*k[2]*k[2] + (0)*c[6]*k[2] - (0)*c[6] + (0)*c[7]*k[0]*k[0] + (0)*c[7]*k[0]*k[1] - (0)*c[7]*k[0]*k[2] + (0)*c[7]*k[0] + (0)*c[7]*k[1]*k[1] + (0)*c[7]*k[1]*k[2] + (0)*c[7]*k[1] + (0)*c[7]*k[2]*k[2] + (0)*c[7]*k[2] - (0)*c[7] + (0)*c[8]*k[0]*k[0] - (0)*c[8]*k[0]*k[1] + (0)*c[8]*k[0]*k[2] - (0)*c[8]*k[0] - (0)*c[8]*k[1]*k[1] - (0)*c[8]*k[1]*k[2] + (0)*c[8]*k[1] + (0)*c[8]*k[2]*k[2] - (0)*c[8]*k[2] + (0)*c[8] - (0)*c[9]*k[0]*k[0] - (0)*c[9]*k[0]*k[1] + (0)*c[9]*k[0]*k[2] - (0)*c[9]*k[0] - (0)*c[9]*k[1]*k[1] - (0)*c[9]*k[1]*k[2] - (0)*c[9]*k[1] + (0)*c[9]*k[2]*k[2] - (0)*c[9]*k[2] + (0)*c[9]",
            "(0)*c[0]*k[0]*k[0] + (0)*c[0]*k[0]*k[1] - (0)*c[0]*k[0]*k[2] + (0)*c[0]*k[0] + (0)*c[0]*k[1]*k[1] + (0)*c[0]*k[1]*k[2] - (0)*c[0]*k[1] + (0)*c[0]*k[2]*k[2] + (0)*c[0]*k[2] - (0)*c[0] + (0)*c[1]*k[0]*k[0] + (0)*c[1]*k[0]*k[1] - (0)*c[1]*k[0]*k[2] + (0)*c[1]*k[0] + (0)*c[1]*k[1]*k[1] + (0)*c[1]*k[1]*k[2] - (0)*c[1]*k[1] + (0)*c[1]*k[2]*k[2] + (0)*c[1]*k[2] - (0)*c[1] + (0)*c[2]*k[0]*k[0] - (0)*c[2]*k[0]*k[1] + (0)*c[2]*k[0]*k[2] - (0)*c[2]*k[0] - (0)*c[2]*k[1]*k[1] - (0)*c[2]*k[1]*k[2] + (0)*c[2]*k[1] - (0)*c[2]*k[2]*k[2] + (0)*c[2]*k[2] + (0)*c[2] + (0)*c[3]*k[0]*k[0] - (0)*c[3]*k[0]*k[1] + (0)*c[3]*k[0]*k[2] + (0)*c[3]*k[0] - (0)*c[3]*k[1]*k[1] - (0)*c[3]*k[1]*k[2] + (0)*c[3]*k[1] - (0)*c[3]*k[2]*k[2] + (0)*c[3]*k[2] + (0)*c[3] - (0)*c[4]*k[0]*k[0] + (0)*c[4]*k[0]*k[1] - (0)*c[4]*k[0]*k[2] - (0)*c[4]*k[0] + (0)*c[4]*k[1]*k[1] + (0)*c[4]*k[1]*k[2] - (0)*c[4]*k[1] + (0)*c[4]*k[2]*k[2] - (0)*c[4]*k[2] - (0)*c[4] + (0)*c[5]*k[0]*k[0] - (0)*c[5]*k[0]*k[1] + (0)*c[5]*k[0]*k[2] + (0)*c[5]*k[0] - (0)*c[5]*k[1]*k[1] - (0)*c[5]*k[1]*k[2] + (0)*c[5]*k[1] - (0)*c[5]*k[2]*k[2] + (0)*c[5]*k[2] + (0)*c[5] + (0)*c[6]*k[0]*k[0] - (0)*c[6]*k[0]*k[1] + (0)*c[6]*k[0]*k[2] - (0)*c[6]*k[0] - (0)*c[6]*k[1]*k[1] - (0)*c[6]*k[1]*k[2] + (0)*c[6]*k[1] - (0)*c[6]*k[2]*k[2] + (0)*c[6]*k[2] + (0)*c[6] - (0)*c[7]*k[0]*k[0] + (0)*c[7]*k[0]*k[1] - (0)*c[7]*k[0]*k[2] - (0)*c[7]*k[0] + (0)*c[7]*k[1]*k[1] + (0)*c[7]*k[1]*k[2] - (0)*c[7]*k[1] + (0)*c[7]*k[2]*k[2] - (0)*c[7]*k[2] - (0)*c[7] - (0)*c[8]*k[0]*k[0] + (0)*c[8]*k[0]*k[1] - (0)*c[8]*k[0]*k[2] + (0)*c[8]*k[0] + (0)*c[8]*k[1]*k[1] + (0)*c[8]*k[1]*k[2] - (0)*c[8]*k[1] + (0)*c[8]*k[2]*k[2] - (0)*c[8]*k[2] - (0)*c[8] - (0)*c[9]*k[0]*k[0] - (0)*c[9]*k[0]*k[1] + (0)*c[9]*k[0]*k[2] - (0)*c[9]*k[0] - (0)*c[9]*k[1]*k[1] - (0)*c[9]*k[1]*k[2] + (0)*c[9]*k[1] - (0)*c[9]*k[2]*k[2] - (0)*c[9]*k[2] + (0)*c[9]",
            "(0)*c[0]*k[0]*k[0] + (0)*c[0]*k[0]*k[1] - (0)*c[0]*k[0]*k[2] + (0)*c[0]*k[0] + (0)*c[0]*k[1]*k[1] + (0)*c[0]*k[1]*k[2] - (0)*c[0]*k[1] + (0)*c[0]*k[2]*k[2] + (0)*c[0]*k[2] - (0)*c[0] + (0)*c[1]*k[0]*k[0] + (0)*c[1]*k[0]*k[1] - (0)*c[1]*k[0]*k[2] + (0)*c[1]*k[0] + (0)*c[1]*k[1]*k[1] + (0)*c[1]*k[1]*k[2] + (0)*c[1]*k[1] - (0)*c[1]*k[2]*k[2] + (0)*c[1]*k[2] - (0)*c[1] - (0)*c[2]*k[0]*k[0] - (0)*c[2]*k[0]*k[1] - (0)*c[2]*k[0]*k[2] + (0)*c[2]*k[0] + (0)*c[2]*k[1]*k[1] - (0)*c[2]*k[1]*k[2] - (0)*c[2]*k[1] - (0)*c[2]*k[2]*k[2] - (0)*c[2]*k[2] + (0)*c[2] - (0)*c[3]*k[0]*k[0] + (0)*c[3]*k[0]*k[1] - (0)*c[3]*k[0]*k[2] - (0)*c[3]*k[0] - (0)*c[3]*k[1]*k[1] - (0)*c[3]*k[1]*k[2] + (0)*c[3]*k[1] - (0)*c[3]*k[2]*k[2] + (0)*c[3]*k[2] - (0)*c[3] + (0)*c[4]*k[0]*k[0] - (0)*c[4]*k[0]*k[1] + (0)*c[4]*k[0]*k[2] + (0)*c[4]*k[0] + (0)*c[4]*k[1]*k[1] + (0)*c[4]*k[1]*k[2] - (0)*c[4]*k[1] + (0)*c[4]*k[2]*k[2] - (0)*c[4]*k[2] + (0)*c[4] - (0)*c[5]*k[0]*k[0] + (0)*c[5]*k[0]*k[1] - (0)*c[5]*k[0]*k[2] + (0)*c[5]*k[0] - (0)*c[5]*k[1]*k[1] - (0)*c[5]*k[1]*k[2] + (0)*c[5]*k[1] - (0)*c[5]*k[2]*k[2] + (0)*c[5]*k[2] - (0)*c[5] - (0)*c[6]*k[0]*k[0] - (0)*c[6]*k[0]*k[1] - (0)*c[6]*k[0]*k[2] + (0)*c[6]*k[0] + (0)*c[6]*k[1]*k[1] - (0)*c[6]*k[1]*k[2] - (0)*c[6]*k[1] - (0)*c[6]*k[2]*k[2] - (0)*c[6]*k[2] + (0)*c[6] + (0)*c[7]*k[0]*k[0] - (0)*c[7]*k[0]*k[1] + (0)*c[7]*k[0]*k[2] - (0)*c[7]*k[0] + (0)*c[7]*k[1]*k[1] + (0)*c[7]*k[1]*k[2] - (0)*c[7]*k[1] + (0)*c[7]*k[2]*k[2] - (0)*c[7]*k[2] + (0)*c[7] + (0)*c[8]*k[0]*k[0] + (0)*c[8]*k[0]*k[1] + (0)*c[8]*k[0]*k[2] - (0)*c[8]*k[0] - (0)*c[8]*k[1]*k[1] + (0)*c[8]*k[1]*k[2] + (0)*c[8]*k[1] + (0)*c[8]*k[2]*k[2] + (0)*c[8]*k[2] - (0)*c[8] - (0)*c[9]*k[0]*k[0] - (0)*c[9]*k[0]*k[1] + (0)*c[9]*k[0]*k[2] - (0)*c[9]*k[0] - (0)*c[9]*k[1]*k[1] - (0)*c[9]*k[1]*k[2] + (0)*c[9]*k[1] + (0)*c[9]*k[2]*k[2] - (0)*c[9]*k[2] + (0)*c[9]",
            "(0)*c[0]*k[0]*k[0] + (0)*c[0]*k[0]*k[1] - (0)*c[0]*k[0]*k[2] + (0)*c[0]*k[0] + (0)*c[0]*k[1]*k[1] + (0)*c[0]*k[1]*k[2] - (0)*c[0]*k[1] + (0)*c[0]*k[2]*k[2] + (0)*c[0]*k[2] - (0)*c[0] + (0)*c[1]*k[0]*k[0] + (0)*c[1]*k[0]*k[1] - (0)*c[1]*k[0]*k[2] + (0)*c[1]*k[0] + (0)*c[1]*k[1]*k[1] + (0)*c[1]*k[1]*k[2] + (0)*c[1]*k[1] - (0)*c[1]*k[2]*k[2] + (0)*c[1]*k[2] - (0)*c[1] + (0)*c[2]*k[0]*k[0] - (0)*c[2]*k[0]*k[1] + (0)*c[2]*k[0]*k[2] - (0)*c[2]*k[0] - (0)*c[2]*k[1]*k[1] - (0)*c[2]*k[1]*k[2] + (0)*c[2]*k[1] - (0)*c[2]*k[2]*k[2] + (0)*c[2]*k[2] + (0)*c[2] - (0)*c[3]*k[0]*k[0] - (0)*c[3]*k[0]*k[1] + (0)*c[3]*k[0]*k[2] - (0)*c[3]*k[0] - (0)*c[3]*k[1]*k[1] - (0)*c[3]*k[1]*k[2] - (0)*c[3]*k[1] - (0)*c[3]*k[2]*k[2] - (0)*c[3]*k[2] + (0)*c[3] + (0)*c[4]*k[0]*k[0] + (0)*c[4]*k[0]*k[1] - (0)*c[4]*k[0]*k[2] + (0)*c[4]*k[0] + (0)*c[4]*k[1]*k[1] + (0)*c[4]*k[1]*k[2] + (0)*c[4]*k[1] + (0)*c[4]*k[2]*k[2] + (0)*c[4]*k[2] - (0)*c[4] - (0)*c[5]*k[0]*k[0] - (0)*c[5]*k[0]*k[1] + (0)*c[5]*k[0]*k[2] - (0)*c[5]*k[0] - (0)*c[5]*k[1]*k[1] - (0)*c[5]*k[1]*k[2] - (0)*c[5]*k[1] - (0)*c[5]*k[2]*k[2] - (0)*c[5]*k[2] + (0)*c[5] + (0)*c[6]*k[0]*k[0] - (0)*c[6]*k[0]*k[1] + (0)*c[6]*k[0]*k[2] - (0)*c[6]*k[0] - (0)*c[6]*k[1]*k[1] - (0)*c[6]*k[1]*k[2] + (0)*c[6]*k[1] - (0)*c[6]*k[2]*k[2] + (0)*c[6]*k[2] + (0)*c[6] + (0)*c[7]*k[0]*k[0] + (0)*c[7]*k[0]*k[1] - (0)*c[7]*k[0]*k[2] + (0)*c[7]*k[0] + (0)*c[7]*k[1]*k[1] + (0)*c[7]*k[1]*k[2] + (0)*c[7]*k[1] + (0)*c[7]*k[2]*k[2] + (0)*c[7]*k[2] - (0)*c[7] - (0)*c[8]*k[0]*k[0] + (0)*c[8]*k[0]*k[1] - (0)*c[8]*k[0]*k[2] + (0)*c[8]*k[0] + (0)*c[8]*k[1]*k[1] + (0)*c[8]*k[1]*k[2] - (0)*c[8]*k[1] + (0)*c[8]*k[2]*k[2] - (0)*c[8]*k[2] - (0)*c[8] - (0)*c[9]*k[0]*k[0] - (0)*c[9]*k[0]*k[1] + (0)*c[9]*k[0]*k[2] - (0)*c[9]*k[0] - (0)*c[9]*k[1]*k[1] - (0)*c[9]*k[1]*k[2] + (0)*c[9]*k[1] - (0)*c[9]*k[2]*k[2] - (0)*c[9]*k[2] + (0)*c[9]",
            "(0)*c[0]*k[0]*k[0] + (0)*c[0]*k[0]*k[1] - (0)*c[0]*k[0]*k[2] + (0)*c[0]*k[0] + (0)*c[0]*k[1]*k[1] + (0)*c[0]*k[1]*k[2] - (0)*c[0]*k[1] + (0)*c[0]*k[2]*k[2] + (0)*c[0]*k[2] - (0)*c[0] + (0)*c[1]*k[0]*k[0] + (0)*c[1]*k[0]*k[1] - (0)*c[1]*k[0]*k[2] + (0)*c[1]*k[0] + (0)*c[1]*k[1]*k[1] + (0)*c[1]*k[1]*k[2] + (0)*c[1]*k[1] - (0)*c[1]*k[2]*k[2] + (0)*c[1]*k[2] - (0)*c[1] - (0)*c[2]*k[0]*k[0] - (0)*c[2]*k[0]*k[1] - (0)*c[2]*k[0]*k[2] + (0)*c[2]*k[0] + (0)*c[2]*k[1]*k[1] - (0)*c[2]*k[1]*k[2] - (0)*c[2]*k[1] - (0)*c[2]*k[2]*k[2] - (0)*c[2]*k[2] + (0)*c[2] - (0)*c[3]*k[0]*k[0] + (0)*c[3]*k[0]*k[1] - (0)*c[3]*k[0]*k[2] - (0)*c[3]*k[0] - (0)*c[3]*k[1]*k[1] - (0)*c[3]*k[1]*k[2] + (0)*c[3]*k[1] - (0)*c[3]*k[2]*k[2] + (0)*c[3]*k[2] - (0)*c[3] + (0)*c[4]*k[0]*k[0] - (0)*c[4]*k[0]*k[1] + (0)*c[4]*k[0]*k[2] + (0)*c[4]*k[0] + (0)*c[4]*k[1]*k[1] + (0)*c[4]*k[1]*k[2] - (0)*c[4]*k[1] + (0)*c[4]*k[2]*k[2] - (0)*c[4]*k[2] + (0)*c[4] - (0)*c[5]*k[0]*k[0] + (0)*c[5]*k[0]*k[1] - (0)*c[5]*k[0]*k[2] + (0)*c[5]*k[0] - (0)*c[5]*k[1]*k[1] - (0)*c[5]*k[1]*k[2] + (0)*c[5]*k[1] - (0)*c[5]*k[2]*k[2] + (0)*c[5]*k[2] - (0)*c[5] - (0)*c[6]*k[0]*k[0] - (0)*c[6]*k[0]*k[1] - (0)*c[6]*k[0]*k[2] + (0)*c[6]*k[0] + (0)*c[6]*k[1]*k[1] - (0)*c[6]*k[1]*k[2] - (0)*c[6]*k[1] - (0)*c[6]*k[2]*k[2] - (0)*c[6]*k[2] + (0)*c[6] + (0)*c[7]*k[0]*k[0] - (0)*c[7]*k[0]*k[1] + (0)*c[7]*k[0]*k[2] - (0)*c[7]*k[0] + (0)*c[7]*k[1]*k[1] + (0)*c[7]*k[1]*k[2] - (0)*c[7]*k[1] + (0)*c[7]*k[2]*k[2] - (0)*c[7]*k[2] + (0)*c[7] + (0)*c[8]*k[0]*k[0] + (0)*c[8]*k[0]*k[1] + (0)*c[8]*k[0]*k[2] - (0)*c[8]*k[0] - (0)*c[8]*k[1]*k[1] + (0)*c[8]*k[1]*k[2] + (0)*c[8]*k[1] + (0)*c[8]*k[2]*k[2] + (0)*c[8]*k[2] - (0)*c[8] - (0)*c[9]*k[0]*k[0] - (0)*c[9]*k[0]*k[1] + (0)*c[9]*k[0]*k[2] - (0)*c[9]*k[0] - (0)*c[9]*k[1]*k[1] - (0)*c[9]*k[1]*k[2] + (0)*c[9]*k[1] + (0)*c[9]*k[2]*k[2] - (0)*c[9]*k[2] + (0)*c[9]",
            "(0)*c[0]*k[0]*k[0] - (0)*c[0]*k[0]*k[1] - (0)*c[0]*k[0]*k[2] + (0)*c[0]*k[0] + (0)*c[0]*k[1]*k[1] + (0)*c[0]*k[1]*k[2] - (0)*c[0]*k[1] - (0)*c[0]*k[2]*k[2] + (0)*c[0]*k[2] - (0)*c[0] + (0)*c[1]*k[0]*k[0] - (0)*c[1]*k[0]*k[1] + (0)*c[1]*k[0]*k[2] - (0)*c[1]*k[0] - (0)*c[1]*k[1]*k[1] + (0)*c[1]*k[1]*k[2] + (0)*c[1]*k[1] + (0)*c[1]*k[2]*k[2] - (0)*c[1]*k[2] + (0)*c[1] - (0)*c[2]*k[0]*k[0] - (0)*c[2]*k[0]*k[1] - (0)*c[2]*k[0]*k[2] + (0)*c[2]*k[0] + (0)*c[2]*k[1]*k[1] + (0)*c[2]*k[1]*k[2] - (0)*c[2]*k[1] + (0)*c[2]*k[2]*k[2] - (0)*c[2]*k[2] + (0)*c[2] + (0)*c[3]*k[0]*k[0] - (0)*c[3]*k[0]*k[1] + (0)*c[3]*k[0]*k[2] - (0)*c[3]*k[0] - (0)*c[3]*k[1]*k[1] - (0)*c[3]*k[1]*k[2] - (0)*c[3]*k[1] + (0)*c[3]*k[2]*k[2] - (0)*c[3]*k[2] + (0)*c[3] - (0)*c[4]*k[0]*k[0] + (0)*c[4]*k[0]*k[1] - (0)*c[4]*k[0]*k[2] + (0)*c[4]*k[0] + (0)*c[4]*k[1]*k[1] + (0)*c[4]*k[1]*k[2] - (0)*c[4]*k[1] - (0)*c[4]*k[2]*k[2] + (0)*c[4]*k[2] - (0)*c[4] + (0)*c[5]*k[0]*k[0] - (0)*c[5]*k[0]*k[1] + (0)*c[5]*k[0]*k[2] - (0)*c[5]*k[0] - (0)*c[5]*k[1]*k[1] - (0)*c[5]*k[1]*k[2] + (0)*c[5]*k[1] + (0)*c[5]*k[2]*k[2] + (0)*c[5]*k[2] + (0)*c[5] - (0)*c[6]*k[0]*k[0] + (0)*c[6]*k[0]*k[1] - (0)*c[6]*k[0]*k[2] + (0)*c[6]*k[0] + (0)*c[6]*k[1]*k[1] + (0)*c[6]*k[1]*k[2] + (0)*c[6]*k[1] - (0)*c[6]*k[2]*k[2] + (0)*c[6]*k[2] - (0)*c[6] + (0)*c[7]*k[0]*k[0] - (0)*c[7]*k[0]*k[1] + (0)*c[7]*k[0]*k[2] - (0)*c[7]*k[0] - (0)*c[7]*k[1]*k[1] - (0)*c[7]*k[1]*k[2] + (0)*c[7]*k[1] + (0)*c[7]*k[2]*k[2] - (0)*c[7]*k[2] + (0)*c[7] + (0)*c[8]*k[0]*k[0] + (0)*c[8]*k[0]*k[1] + (0)*c[8]*k[0]*k[2] - (0)*c[8]*k[0] - (0)*c[8]*k[1]*k[1] + (0)*c[8]*k[1]*k[2] + (0)*c[8]*k[1] - (0)*c[8]*k[2]*k[2] + (0)*c[8]*k[2] - (0)*c[8] + (0)*c[9]*k[0]*k[0] - (0)*c[9]*k[0]*k[1] + (0)*c[9]*k[0]*k[2] - (0)*c[9]*k[0] - (0)*c[9]*k[1]*k[1] - (0)*c[9]*k[1]*k[2] - (0)*c[9]*k[1] + (0)*c[9]*k[2]*k[2] - (0)*c[9]*k[2] + (0)*c[9]",
            "(0)*c[0]*k[0]*k[0] + (0)*c[0]*k[0]*k[1] - (0)*c[0]*k[0]*k[2] + (0)*c[0]*k[0] + (0)*c[0]*k[1]*k[1] + (0)*c[0]*k[1]*k[2] - (0)*c[0]*k[1] - (0)*c[0]*k[2]*k[2] + (0)*c[0]*k[2] - (0)*c[0] + (0)*c[1]*k[0]*k[0] - (0)*c[1]*k[0]*k[1] + (0)*c[1]*k[0]*k[2] - (0)*c[1]*k[0] - (0)*c[1]*k[1]*k[1] - (0)*c[1]*k[1]*k[2] + (0)*c[1]*k[1] - (0)*c[1]*k[2]*k[2] - (0)*c[1]*k[2] + (0)*c[1] + (0)*c[2]*k[0]*k[0] + (0)*c[2]*k[0]*k[1] + (0)*c[2]*k[0]*k[2] - (0)*c[2]*k[0] + (0)*c[2]*k[1]*k[1] + (0)*c[2]*k[1]*k[2] + (0)*c[2]*k[1] + (0)*c[2]*k[2]*k[2] + (0)*c[2]*k[2] - (0)*c[2] + (0)*c[3]*k[0]*k[0] - (0)*c[3]*k[0]*k[1] - (0)*c[3]*k[0]*k[2] + (0)*c[3]*k[0] - (0)*c[3]*k[1]*k[1] - (0)*c[3]*k[1]*k[2] + (0)*c[3]*k[1] - (0)*c[3]*k[2]*k[2] + (0)*c[3]*k[2] + (0)*c[3] - (0)*c[4]*k[0]*k[0] - (0)*c[4]*k[0]*k[1] + (0)*c[4]*k[0]*k[2] - (0)*c[4]*k[0] - (0)*c[4]*k[1]*k[1] - (0)*c[4]*k[1]*k[2] - (0)*c[4]*k[1] + (0)*c[4]*k[2]*k[2] - (0)*c[4]*k[2] + (0)*c[4] + (0)*c[5]*k[0]*k[0] - (0)*c[5]*k[0]*k[1] - (0)*c[5]*k[0]*k[2] + (0)*c[5]*k[0] - (0)*c[5]*k[1]*k[1] - (0)*c[5]*k[1]*k[2] + (0)*c[5]*k[1] - (0)*c[5]*k[2]*k[2] + (0)*c[5]*k[2] + (0)*c[5] + (0)*c[6]*k[0]*k[0] - (0)*c[6]*k[0]*k[1] - (0)*c[6]*k[0]*k[2] + (0)*c[6]*k[0] + (0)*c[6]*k[1]*k[1] - (0)*c[6]*k[1]*k[2] + (0)*c[6]*k[1] - (0)*c[6]*k[2]*k[2] + (0)*c[6]*k[2] - (0)*c[6] + (0)*c[7]*k[0]*k[0] + (0)*c[7]*k[0]*k[1] - (0)*c[7]*k[0]*k[2] + (0)*c[7]*k[0] + (0)*c[7]*k[1]*k[1] + (0)*c[7]*k[1]*k[2] + (0)*c[7]*k[1] + (0)*c[7]*k[2]*k[2] + (0)*c[7]*k[2] - (0)*c[7] + (0)*c[8]*k[0]*k[0] - (0)*c[8]*k[0]*k[1] + (0)*c[8]*k[0]*k[2] - (0)*c[8]*k[0] - (0)*c[8]*k[1]*k[1] - (0)*c[8]*k[1]*k[2] + (0)*c[8]*k[1] + (0)*c[8]*k[2]*k[2] - (0)*c[8]*k[2] + (0)*c[8] - (0)*c[9]*k[0]*k[0] - (0)*c[9]*k[0]*k[1] + (0)*c[9]*k[0]*k[2] - (0)*c[9]*k[0] - (0)*c[9]*k[1]*k[1] - (0)*c[9]*k[1]*k[2] - (0)*c[9]*k[1] + (0)*c[9]*k[2]*k[2] - (0)*c[9]*k[2] + (0)*c[9]",
            "(0)*c[0]*k[0]*k[0] + (0)*c[0]*k[0]*k[1] - (0)*c[0]*k[0]*k[2] + (0)*c[0]*k[0] + (0)*c[0]*k[1]*k[1] + (0)*c[0]*k[1]*k[2] - (0)*c[0]*k[1] + (0)*c[0]*k[2]*k[2] + (0)*c[0]*k[2] - (0)*c[0] + (0)*c[1]*k[0]*k[0] + (0)*c[1]*k[0]*k[1] - (0)*c[1]*k[0]*k[2] + (0)*c[1]*k[0] + (0)*c[1]*k[1]*k[1] + (0)*c[1]*k[1]*k[2] + (0)*c[1]*k[1] - (0)*c[1]*k[2]*k[2] + (0)*c[1]*k[2] - (0)*c[1] + (0)*c[2]*k[0]*k[0] - (0)*c[2]*k[0]*k[1] + (0)*c[2]*k[0]*k[2] - (0)*c[2]*k[0] - (0)*c[2]*k[1]*k[1] - (0)*c[2]*k[1]*k[2] + (0)*c[2]*k[1] - (0)*c[2]*k[2]*k[2] + (0)*c[2]*k[2] + (0)*c[2] - (0)*c[3]*k[0]*k[0] - (0)*c[3]*k[0]*k[1] + (0)*c[3]*k[0]*k[2] - (0)*c[3]*k[0] - (0)*c[3]*k[1]*k[1] - (0)*c[3]*k[1]*k[2] - (0)*c[3]*k[1] - (0)*c[3]*k[2]*k[2] - (0)*c[3]*k[2] + (0)*c[3] + (0)*c[4]*k[0]*k[0] + (0)*c[4]*k[0]*k[1] - (0)*c[4]*k[0]*k[2] + (0)*c[4]*k[0] + (0)*c[4]*k[1]*k[1] + (0)*c[4]*k[1]*k[2] + (0)*c[4]*k[1] + (0)*c[4]*k[2]*k[2] + (0)*c[4]*k[2] - (0)*c[4] - (0)*c[5]*k[0]*k[0] - (0)*c[5]*k[0]*k[1] + (0)*c[5]*k[0]*k[2] - (0)*c[5]*k[0] - (0)*c[5]*k[1]*k[1] - (0)*c[5]*k[1]*k[2] - (0)*c[5]*k[1] - (0)*c[5]*k[2]*k[2] - (0)*c[5]*k[2] + (0)*c[5] + (0)*c[6]*k[0]*k[0] - (0)*c[6]*k[0]*k[1] + (0)*c[6]*k[0]*k[2] - (0)*c[6]*k[0] - (0)*c[6]*k[1]*k[1] - (0)*c[6]*k[1]*k[2] + (0)*c[6]*k[1] - (0)*c[6]*k[2]*k[2] + (0)*c[6]*k[2] + (0)*c[6] + (0)*c[7]*k[0]*k[0] + (0)*c[7]*k[0]*k[1] - (0)*c[7]*k[0]*k[2] + (0)*c[7]*k[0] + (0)*c[7]*k[1]*k[1] + (0)*c[7]*k[1]*k[2] + (0)*c[7]*k[1] + (0)*c[7]*k[2]*k[2] + (0)*c[7]*k[2] - (0)*c[7] - (0)*c[8]*k[0]*k[0] + (0)*c[8]*k[0]*k[1] - (0)*c[8]*k[0]*k[2] + (0)*c[8]*k[0] + (0)*c[8]*k[1]*k[1] + (0)*c[8]*k[1]*k[2] - (0)*c[8]*k[1] + (0)*c[8]*k[2]*k[2] - (0)*c[8]*k[2] - (0)*c[8] - (0)*c[9]*k[0]*k[0] - (0)*c[9]*k[0]*k[1] + (0)*c[9]*k[0]*k[2] - (0)*c[9]*k[0] - (0)*c[9]*k[1]*k[1] - (0)*c[9]*k[1]*k[2] + (0)*c[9]*k[1] - (0)*c[9]*k[2]*k[2] - (0)*c[9]*k[2] + (0)*c[9]",
            "(0)*c[0]*k[0]*k[0] + (0)*c[0]*k[0]*k[1] - (0)*c[0]*k[0]*k[2] + (0)*c[0]*k[0] + (0)*c[0]*k[1]*k[1] + (0)*c[0]*k[1]*k[2] - (0)*c[0]*k[1] - (0)*c[0]*k[2]*k[2] + (0)*c[0]*k[2] - (0)*c[0] + (0)*c[1]*k[0]*k[0] - (0)*c[1]*k[0]*k[1] + (0)*c[1]*k[0]*k[2] - (0)*c[1]*k[0] - (0)*c[1]*k[1]*k[1] - (0)*c[1]*k[1]*k[2] + (0)*c[1]*k[1] - (0)*c[1]*k[2]*k[2] - (0)*c[1]*k[2] + (0)*c[1] + (0)*c[2]*k[0]*k[0] + (0)*c[2]*k[0]*k[1] + (0)*c[2]*k[0]*k[2] - (0)*c[2]*k[0] + (0)*c[2]*k[1]*k[1] + (0)*c[2]*k[1]*k[2] + (0)*c[2]*k[1] + (0)*c[2]*k[2]*k[2] + (0)*c[2]*k[2] - (0)*c[2] + (0)*c[3]*k[0]*k[0] - (0)*c[3]*k[0]*k[1] - (0)*c[3]*k[0]*k[2] + (0)*c[3]*k[0] - (0)*c[3]*k[1]*k[1] - (0)*c[3]*k[1]*k[2] + (0)*c[3]*k[1] - (0)*c[3]*k[2]*k[2] + (0)*c[3]*k[2] + (0)*c[3] - (0)*c[4]*k[0]*k[0] - (0)*c[4]*k[0]*k[1] + (0)*c[4]*k[0]*k[2] - (0)*c[4]*k[0] - (0)*c[4]*k[1]*k[1] - (0)*c[4]*k[1]*k[2] - (0)*c[4]*k[1] + (0)*c[4]*k[2]*k[2] - (0)*c[4]*k[2] + (0)*c[4] + (0)*c[5]*k[0]*k[0] - (0)*c[5]*k[0]*k[1] - (0)*c[5]*k[0]*k[2] + (0)*c[5]*k[0] - (0)*c[5]*k[1]*k[1] - (0)*c[5]*k[1]*k[2] + (0)*c[5]*k[1] - (0)*c[5]*k[2]*k[2] + (0)*c[5]*k[2] + (0)*c[5] + (0)*c[6]*k[0]*k[0] - (0)*c[6]*k[0]*k[1] - (0)*c[6]*k[0]*k[2] + (0)*c[6]*k[0] + (0)*c[6]*k[1]*k[1] - (0)*c[6]*k[1]*k[2] + (0)*c[6]*k[1] - (0)*c[6]*k[2]*k[2] + (0)*c[6]*k[2] - (0)*c[6] + (0)*c[7]*k[0]*k[0] + (0)*c[7]*k[0]*k[1] - (0)*c[7]*k[0]*k[2] + (0)*c[7]*k[0] + (0)*c[7]*k[1]*k[1] + (0)*c[7]*k[1]*k[2] + (0)*c[7]*k[1] + (0)*c[7]*k[2]*k[2] + (0)*c[7]*k[2] - (0)*c[7] + (0)*c[8]*k[0]*k[0] - (0)*c[8]*k[0]*k[1] + (0)*c[8]*k[0]*k[2] - (0)*c[8]*k[0] - (0)*c[8]*k[1]*k[1] - (0)*c[8]*k[1]*k[2] + (0)*c[8]*k[1] + (0)*c[8]*k[2]*k[2] - (0)*c[8]*k[2] + (0)*c[8] - (0)*c[9]*k[0]*k[0] - (0)*c[9]*k[0]*k[1] + (0)*c[9]*k[0]*k[2] - (0)*c[9]*k[0] - (0)*c[9]*k[1]*k[1] - (0)*c[9]*k[1]*k[2] - (0)*c[9]*k[1] + (0)*c[9]*k[2]*k[2] - (0)*c[9]*k[2] + (0)*c[9]",
            "(0)*c[0]*k[0]*k[0] - (0)*c[0]*k[0]*k[1] - (0)*c[0]*k[0]*k[2] + (0)*c[0]*k[0] + (0)*c[0]*k[1]*k[1] - (0)*c[0]*k[1]*k[2] - (0)*c[0]*k[1] - (0)*c[0]*k[2]*k[2] + (0)*c[0]*k[2] - (0)*c[0] + (0)*c[1]*k[0]*k[0] - (0)*c[1]*k[0]*k[1] + (0)*c[1]*k[0]*k[2] - (0)*c[1]*k[0] - (0)*c[1]*k[1]*k[1] - (0)*c[1]*k[1]*k[2] + (0)*c[1]*k[1] + (0)*c[1]*k[2]*k[2] - (0)*c[1]*k[2] + (0)*c[1] - (0)*c[2]*k[0]*k[0] + (0)*c[2]*k[0]*k[1] - (0)*c[2]*k[0]*k[2] - (0)*c[2]*k[0] + (0)*c[2]*k[1]*k[1] + (0)*c[2]*k[1]*k[2] - (0)*c[2]*k[1] + (0)*c[2]*k[2]*k[2] - (0)*c[2]*k[2] - (0)*c[2] - (0)*c[3]*k[0]*k[0] + (0)*c[3]*k[0]*k[1] + (0)*c[3]*k[0]*k[2] - (0)*c[3]*k[0] + (0)*c[3]*k[1]*k[1] + (0)*c[3]*k[1]*k[2] - (0)*c[3]*k[1] + (0)*c[3]*k[2]*k[2] - (0)*c[3]*k[2] + (0)*c[3] + (0)*c[4]*k[0]*k[0] - (0)*c[4]*k[0]*k[1] - (0)*c[4]*k[0]*k[2] - (0)*c[4]*k[0] - (0)*c[4]*k[1]*k[1] - (0)*c[4]*k[1]*k[2] + (0)*c[4]*k[1] - (0)*c[4]*k[2]*k[2] + (0)*c[4]*k[2] + (0)*c[4] + (0)*c[5]*k[0]*k[0] - (0)*c[5]*k[0]*k[1] - (0)*c[5]*k[0]*k[2] + (0)*c[5]*k[0] - (0)*c[5]*k[1]*k[1] - (0)*c[5]*k[1]*k[2] + (0)*c[5]*k[1] - (0)*c[5]*k[2]*k[2] + (0)*c[5]*k[2] - (0)*c[5] + (0)*c[6]*k[0]*k[0] - (0)*c[6]*k[0]*k[1] + (0)*c[6]*k[0]*k[2] - (0)*c[6]*k[0] - (0)*c[6]*k[1]*k[1] - (0)*c[6]*k[1]*k[2] + (0)*c[6]*k[1] - (0)*c[6]*k[2]*k[2] - (0)*c[6]*k[2] + (0)*c[6] + (0)*c[7]*k[0]*k[0] + (0)*c[7]*k[0]*k[1] + (0)*c[7]*k[0]*k[2] - (0)*c[7]*k[0] + (0)*c[7]*k[1]*k[1] + (0)*c[7]*k[1]*k[2] + (0)*c[7]*k[1] + (0)*c[7]*k[2]*k[2] + (0)*c[7]*k[2] - (0)*c[7] - (0)*c[8]*k[0]*k[0] + (0)*c[8]*k[0]*k[1] - (0)*c[8]*k[0]*k[2] + (0)*c[8]*k[0] + (0)*c[8]*k[1]*k[1] + (0)*c[8]*k[1]*k[2] - (0)*c[8]*k[1] + (0)*c[8]*k[2]*k[2] - (0)*c[8]*k[2] - (0)*c[8] - (0)*c[9]*k[0]*k[0] - (0)*c[9]*k[0]*k[1] + (0)*c[9]*k[0]*k[2] - (0)*c[9]*k[0] - (0)*c[9]*k[1]*k[1] - (0)*c[9]*k[1]*k[2] - (0)*c[9]*k[1] + (0)*c[9]*k[2]*k[2] - (0)*c[9]*k[2] + (0)*c[9]"
        ],
        "1": [
            "(0)*c[0]*k[0]*k[0] - (0)*c[0]*k[0]*k[1] - (0)*c[0]*k[0]*k[2] + 4.0*c[0]*k[0] + (0)*c[0]*k[1]*k[1] - (0)*c[0]*k[1]*k[2] + 4.0*c[0]*k[1] - (0)*c[0]*k[2]*k[2] + 4.0*c[0]*k[2] - 3.0*c[0] + (0)*c[1]*k[0]*k[0] - (0)*c[1]*k[0]*k[1] - (0)*c[1]*k[0]*k[2] + 4.0*c[1]*k[0] - (0)*c[1]*k[1]*k[1] - (0)*c[1]*k[1]*k[2] + (0)*c[1]*k[1] - (0)*c[1]*k[2]*k[2] - (0)*c[1]*k[2] - 1.0*c[1] + (0)*c[2]*k[0]*k[0] - (0)*c[2]*k[0]*k[1] + (0)*c[2]*k[0]*k[2] - (0)*c[2]*k[0] - (0)*c[2]*k[1]*k[1] - (0)*c[2]*k[1]*k[2] + (0)*c[2]*k[1] + (0)*c[2]*k[2]*k[2] - (0)*c[2]*k[2] + (0)*c[2] + (0)*c[3]*k[0]*k[0] - (0)*c[3]*k[0]*k[1] + (0)*c[3]*k[0]*k[2] - (0)*c[3]*k[0] - (0)*c[3]*k[1]*k[1] - (0)*c[3]*k[1]*k[2] - (0)*c[3]*k[1] + (0)*c[3]*k[2]*k[2] + (0)*c[3]*k[2] + (0)*c[3] - (0)*c[4]*k[0]*k[0] + (0)*c[4]*k[0]*k[1] - (0)*c[4]*k[0]*k[2] + (0)*c[4]*k[0] + (0)*c[4]*k[1]*k[1] + (0)*c[4]*k[1]*k[2] + (0)*c[4]*k[1] - (0)*c[4]*k[2]*k[2] - (0)*c[4]*k[2] - (0)*c[4] + (0)*c[5]*k[0]*k[0] - (0)*c[5]*k[0]*k[1] + (0)*c[5]*k[0]*k[2] - (0)*c[5]*k[0] - (0)*c[5]*k[1]*k[1] - (0)*c[5]*k[1]*k[2] + (0)*c[5]*k[1] + (0)*c[5]*k[2]*k[2] + 4.0*c[5]*k[2] + (0)*c[5] + (0)*c[6]*k[0]*k[0] - (0)*c[6]*k[0]*k[1] + (0)*c[6]*k[0]*k[2] - (0)*c[6]*k[0] - (0)*c[6]*k[1]*k[1] - (0)*c[6]*k[1]*k[2] + 4.0*c[6]*k[1] + (0)*c[6]*k[2]*k[2] - (0)*c[6]*k[2] + (0)*c[6] - (0)*c[7]*k[0]*k[0] + (0)*c[7]*k[0]*k[1] - (0)*c[7]*k[0]*k[2] + (0)*c[7]*k[0] + (0)*c[7]*k[1]*k[1] + (0)*c[7]*k[1]*k[2] - (0)*c[7]*k[1] - (0)*c[7]*k[2]*k[2] - 4.0*c[7]*k[2] - (0)*c[7] - (0)*c[8]*k[0]*k[0] + (0)*c[8]*k[0]*k[1] - (0)*c[8]*k[0]*k[2] + (0)*c[8]*k[0] + (0)*c[8]*k[1]*k[1] + (0)*c[8]*k[1]*k[2] - 4.00000000000001*c[8]*k[1] - (0)*c[8]*k[2]*k[2] + (0)*c[8]*k[2] - (0)*c[8] - (0)*c[9]*k[0]*k[0] + (0)*c[9]*k[0]*k[1] + (0)*c[9]*k[0]*k[2] - 8.0*c[9]*k[0] - (0)*c[9]*k[1]*k[1] + (0)*c[9]*k[1]*k[2] - 4.0*c[9]*k[1] + (0)*c[9]*k[2]*k[2] - 4.0*c[9]*k[2] + 4.0*c[9]",
            "(0)*c[0]*k[0]*k[0] - (0)*c[0]*k[0]*k[1] - (0)*c[0]*k[0]*k[2] + 4.0*c[0]*k[0] + (0)*c[0]*k[1]*k[1] + (0)*c[0]*k[1]*k[2] + 4.0*c[0]*k[1] + (0)*c[0]*k[2]*k[2] + 4.0*c[0]*k[2] - 3.0*c[0] + (0)*c[1]*k[0]*k[0] + (0)*c[1]*k[0]*k[1] + (0)*c[1]*k[0]*k[2] - (0)*c[1]*k[0] + (0)*c[1]*k[1]*k[1] + (0)*c[1]*k[1]*k[2] - (0)*c[1]*k[1] + (0)*c[1]*k[2]*k[2] - (0)*c[1]*k[2] - (0)*c[1] + (0)*c[2]*k[0]*k[0] + (0)*c[2]*k[0]*k[1] + (0)*c[2]*k[0]*k[2] - (0)*c[2]*k[0] + (0)*c[2]*k[1]*k[1] - (0)*c[2]*k[1]*k[2] + 4.0*c[2]*k[1] - (0)*c[2]*k[2]*k[2] + (0)*c[2]*k[2] - 1.0*c[2] - (0)*c[3]*k[0]*k[0] + (0)*c[3]*k[0]*k[1] + (0)*c[3]*k[0]*k[2] - (0)*c[3]*k[0] + (0)*c[3]*k[1]*k[1] + (0)*c[3]*k[1]*k[2] - (0)*c[3]*k[1] + (0)*c[3]*k[2]*k[2] - (0)*c[3]*k[2] - (0)*c[3] + (0)*c[4]*k[0]*k[0] - (0)*c[4]*k[0]*k[1] + (0)*c[4]*k[0]*k[2] - (0)*c[4]*k[0] - (0)*c[4]*k[1]*k[1] - (0)*c[4]*k[1]*k[2] + (0)*c[4]*k[1] + (0)*c[4]*k[2]*k[2] + 4.0*c[4]*k[2] + (0)*c[4] - (0)*c[5]*k[0]*k[0] + (0)*c[5]*k[0]*k[1] + (0)*c[5]*k[0]*k[2] - (0)*c[5]*k[0] - (0)*c[5]*k[1]*k[1] + (0)*c[5]*k[1]*k[2] - (0)*c[5]*k[1] + (0)*c[5]*k[2]*k[2] - (0)*c[5]*k[2] + (0)*c[5] - (0)*c[6]*k[0]*k[0] - (0)*c[6]*k[0]*k[1] - (0)*c[6]*k[0]*k[2] + 4.00000000000001*c[6]*k[0] - (0)*c[6]*k[1]*k[1] - (0)*c[6]*k[1]*k[2] + (0)*c[6]*k[1] + (0)*c[6]*k[2]*k[2] - (0)*c[6]*k[2] + (0)*c[6] - (0)*c[7]*k[0]*k[0] + (0)*c[7]*k[0]*k[1] - (0)*c[7]*k[0]*k[2] + (0)*c[7]*k[0] + (0)*c[7]*k[1]*k[1] + (0)*c[7]*k[1]*k[2] - (0)*c[7]*k[1] - (0)*c[7]*k[2]*k[2] - 4.0*c[7]*k[2] - (0)*c[7] + (0)*c[8]*k[0]*k[0] - (0)*c[8]*k[0]*k[1] + (0)*c[8]*k[0]*k[2] - 4.00000000000001*c[8]*k[0] - (0)*c[8]*k[1]*k[1] - (0)*c[8]*k[1]*k[2] - 8.0*c[8]*k[1] - (0)*c[8]*k[2]*k[2] - 4.0*c[8]*k[2] + 4.0*c[8] - (0)*c[9]*k[0]*k[0] + (0)*c[9]*k[0]*k[1] + (0)*c[9]*k[0]*k[2] - 4.0*c[9]*k[0] + (0)*c[9]*k[1]*k[1] + (0)*c[9]*k[1]*k[2] - (0)*c[9]*k[1] + (0)*c[9]*k[2]*k[2] - (0)*c[9]*k[2] - (0)*c[9]",
            "(0)*c[0]*k[0]*k[0] - (0)*c[0]*k[0]*k[1] - (0)*c[0]*k[0]*k[2] + 4.0*c[0]*k[0] + (0)*c[0]*k[1]*k[1] + (0)*c[0]*k[1]*k[2] + 4.0*c[0]*k[1] + (0)*c[0]*k[2]*k[2] + 4.0*c[0]*k[2] - 3.0*c[0] - (0)*c[1]*k[0]*k[0] + (0)*c[1]*k[0]*k[1] + (0)*c[1]*k[0]*k[2] - (0)*c[1]*k[0] + (0)*c[1]*k[1]*k[1] + (0)*c[1]*k[1]*k[2] - (0)*c[1]*k[1] + (0)*c[1]*k[2]*k[2] - (0)*c[1]*k[2] - (0)*c[1] + (0)*c[2]*k[0]*k[0] - (0)*c[2]*k[0]*k[1] - (0)*c[2]*k[0]*k[2] + (0)*c[2]*k[0] + (0)*c[2]*k[1]*k[1] + (0)*c[2]*k[1]*k[2] + (0)*c[2]*k[1] - (0)*c[2]*k[2]*k[2] + (0)*c[2]*k[2] - (0)*c[2] + (0)*c[3]*k[0]*k[0] + (0)*c[3]*k[0]*k[1] + (0)*c[3]*k[0]*k[2] - (0)*c[3]*k[0] + (0)*c[3]*k[1]*k[1] + (0)*c[3]*k[1]*k[2] - (0)*c[3]*k[1] - (0)*c[3]*k[2]*k[2] + 4.0*c[3]*k[2] - 1.0*c[3] - (0)*c[4]*k[0]*k[0] - (0)*c[4]*k[0]*k[1] - (0)*c[4]*k[0]*k[2] + (0)*c[4]*k[0] - (0)*c[4]*k[1]*k[1] - (0)*c[4]*k[1]*k[2] + 4.00000000000001*c[4]*k[1] + (0)*c[4]*k[2]*k[2] - (0)*c[4]*k[2] + (0)*c[4] + (0)*c[5]*k[0]*k[0] - (0)*c[5]*k[0]*k[1] - (0)*c[5]*k[0]*k[2] + 4.00000000000001*c[5]*k[0] - (0)*c[5]*k[1]*k[1] - (0)*c[5]*k[1]*k[2] + (0)*c[5]*k[1] + (0)*c[5]*k[2]*k[2] + (0)*c[5]*k[2] + (0)*c[5] + (0)*c[6]*k[0]*k[0] + (0)*c[6]*k[0]*k[1] + (0)*c[6]*k[0]*k[2] - (0)*c[6]*k[0] - (0)*c[6]*k[1]*k[1] - (0)*c[6]*k[1]*k[2] - (0)*c[6]*k[1] + (0)*c[6]*k[2]*k[2] - (0)*c[6]*k[2] - (0)*c[6] - (0)*c[7]*k[0]*k[0] - (0)*c[7]*k[0]*k[1] + (0)*c[7]*k[0]*k[2] - 4.0*c[7]*k[0] - (0)*c[7]*k[1]*k[1] - (0)*c[7]*k[1]*k[2] - 3.99999999999999*c[7]*k[1] - (0)*c[7]*k[2]*k[2] - 8.0*c[7]*k[2] + 4.0*c[7] - (0)*c[8]*k[0]*k[0] + (0)*c[8]*k[0]*k[1] - (0)*c[8]*k[0]*k[2] + (0)*c[8]*k[0] + (0)*c[8]*k[1]*k[1] + (0)*c[8]*k[1]*k[2] - 4.00000000000001*c[8]*k[1] - (0)*c[8]*k[2]*k[2] + (0)*c[8]*k[2] - (0)*c[8] + (0)*c[9]*k[0]*k[0] + (0)*c[9]*k[0]*k[1] + (0)*c[9]*k[0]*k[2] - 4.0*c[9]*k[0] + (0)*c[9]*k[1]*k[1] + (0)*c[9]*k[1]*k[2] - (0)*c[9]*k[1] + (0)*c[9]*k[2]*k[2] - (0)*c[9]*k[2] + (0)*c[9]"
        ],
        "2": [
            "(0)*c[0]*k[0]*k[0] - (0)*c[0]*k[0]*k[1] + (0)*c[0]*k[0]*k[2] - (0)*c[0]*k[0] - (0)*c[0]*k[1]*k[1] - (0)*c[0]*k[1]*k[2] + (0)*c[0]*k[1] + (0)*c[0]*k[2]*k[2] - (0)*c[0]*k[2] + 4.0*c[0] + (0)*c[1]*k[0]*k[0] - (0)*c[1]*k[0]*k[1] + (0)*c[1]*k[0]*k[2] - (0)*c[1]*k[0] - (0)*c[1]*k[1]*k[1] - (0)*c[1]*k[1]*k[2] + (0)*c[1]*k[1] + (0)*c[1]*k[2]*k[2] - (0)*c[1]*k[2] + 4.0*c[1] - (0)*c[2]*k[0]*k[0] - (0)*c[2]*k[0]*k[1] - (0)*c[2]*k[0]*k[2] + (0)*c[2]*k[0] + (0)*c[2]*k[1]*k[1] + (0)*c[2]*k[1]*k[2] - (0)*c[2]*k[1] - (0)*c[2]*k[2]*k[2] + (0)*c[2]*k[2] - (0)*c[2] - (0)*c[3]*k[0]*k[0] + (0)*c[3]*k[0]*k[1] - (0)*c[3]*k[0]*k[2] + (0)*c[3]*k[0] + (0)*c[3]*k[1]*k[1] + (0)*c[3]*k[1]*k[2] - (0)*c[3]*k[1] - (0)*c[3]*k[2]*k[2] + (0)*c[3]*k[2] - (0)*c[3] + (0)*c[4]*k[0]*k[0] - (0)*c[4]*k[0]*k[1] + (0)*c[4]*k[0]*k[2] - (0)*c[4]*k[0] - (0)*c[4]*k[1]*k[1] - (0)*c[4]*k[1]*k[2] + (0)*c[4]*k[1] + (0)*c[4]*k[2]*k[2] - (0)*c[4]*k[2] + (0)*c[4] - (0)*c[5]*k[0]*k[0] + (0)*c[5]*k[0]*k[1] - (0)*c[5]*k[0]*k[2] + (0)*c[5]*k[0] + (0)*c[5]*k[1]*k[1] + (0)*c[5]*k[1]*k[2] - (0)*c[5]*k[1] - (0)*c[5]*k[2]*k[2] + (0)*c[5]*k[2] - (0)*c[5] - (0)*c[6]*k[0]*k[0] - (0)*c[6]*k[0]*k[1] - (0)*c[6]*k[0]*k[2] + (0)*c[6]*k[0] + (0)*c[6]*k[1]*k[1] + (0)*c[6]*k[1]*k[2] - (0)*c[6]*k[1] - (0)*c[6]*k[2]*k[2] + (0)*c[6]*k[2] - (0)*c[6] + (0)*c[7]*k[0]*k[0] - (0)*c[7]*k[0]*k[1] + (0)*c[7]*k[0]*k[2] - (0)*c[7]*k[0] - (0)*c[7]*k[1]*k[1] - (0)*c[7]*k[1]*k[2] + (0)*c[7]*k[1] + (0)*c[7]*k[2]*k[2] - (0)*c[7]*k[2] + (0)*c[7] + (0)*c[8]*k[0]*k[0] + (0)*c[8]*k[0]*k[1] + (0)*c[8]*k[0]*k[2] - (0)*c[8]*k[0] - (0)*c[8]*k[1]*k[1] - (0)*c[8]*k[1]*k[2] + (0)*c[8]*k[1] + (0)*c[8]*k[2]*k[2] - (0)*c[8]*k[2] + (0)*c[8] - (0)*c[9]*k[0]*k[0] + (0)*c[9]*k[0]*k[1] - (0)*c[9]*k[0]*k[2] + (0)*c[9]*k[0] + (0)*c[9]*k[1]*k[1] + (0)*c[9]*k[1]*k[2] - (0)*c[9]*k[1] - (0)*c[9]*k[2]*k[2] + (0)*c[9]*k[2] - 8.0*c[9]",
            "(0)*c[0]*k[0]*k[0] - (0)*c[0]*k[0]*k[1] + (0)*c[0]*k[0]*k[2] - (0)*c[0]*k[0] - (0)*c[0]*k[1]*k[1] - (0)*c[0]*k[1]*k[2] + (0)*c[0]*k[1] + (0)*c[0]*k[2]*k[2] - (0)*c[0]*k[2] + 4.0*c[0] - (0)*c[1]*k[0]*k[0] + (0)*c[1]*k[0]*k[1] + (0)*c[1]*k[0]*k[2] - (0)*c[1]*k[0] - (0)*c[1]*k[1]*k[1] + (0)*c[1]*k[1]*k[2] - (0)*c[1]*k[1] + (0)*c[1]*k[2]*k[2] - (0)*c[1]*k[2] + (0)*c[1] + (0)*c[2]*k[0]*k[0] - (0)*c[2]*k[0]*k[1] + (0)*c[2]*k[0]*k[2] - (0)*c[2]*k[0] - (0)*c[2]*k[1]*k[1] - (0)*c[2]*k[1]*k[2] + (0)*c[2]*k[1] - (0)*c[2]*k[2]*k[2] + (0)*c[2]*k[2] + (0)*c[2] - (0)*c[3]*k[0]*k[0] + (0)*c[3]*k[0]*k[1] - (0)*c[3]*k[0]*k[2] - (0)*c[3]*k[0] + (0)*c[3]*k[1]*k[1] + (0)*c[3]*k[1]*k[2] - (0)*c[3]*k[1] + (0)*c[3]*k[2]*k[2] - (0)*c[3]*k[2] - (0)*c[3] + (0)*c[4]*k[0]*k[0] - (0)*c[4]*k[0]*k[1] + (0)*c[4]*k[0]*k[2] + (0)*c[4]*k[0] - (0)*c[4]*k[1]*k[1] - (0)*c[4]*k[1]*k[2] + (0)*c[4]*k[1] - (0)*c[4]*k[2]*k[2] + (0)*c[4]*k[2] + (0)*c[4] - (0)*c[5]*k[0]*k[0] + (0)*c[5]*k[0]*k[1] + (0)*c[5]*k[0]*k[2] - (0)*c[5]*k[0] - (0)*c[5]*k[1]*k[1] + (0)*c[5]*k[1]*k[2] - (0)*c[5]*k[1] + (0)*c[5]*k[2]*k[2] - (0)*c[5]*k[2] + (0)*c[5] + (0)*c[6]*k[0]*k[0] - (0)*c[6]*k[0]*k[1] + (0)*c[6]*k[0]*k[2] - (0)*c[6]*k[0] - (0)*c[6]*k[1]*k[1] - (0)*c[6]*k[1]*k[2] + (0)*c[6]*k[1] - (0)*c[6]*k[2]*k[2] + (0)*c[6]*k[2] + 4.0*c[6] + (0)*c[7]*k[0]*k[0] - (0)*c[7]*k[0]*k[1] - (0)*c[7]*k[0]*k[2] + (0)*c[7]*k[0] + (0)*c[7]*k[1]*k[1] - (0)*c[7]*k[1]*k[2] + (0)*c[7]*k[1] - (0)*c[7]*k[2]*k[2] + (0)*c[7]*k[2] - (0)*c[7] - (0)*c[8]*k[0]*k[0] + (0)*c[8]*k[0]*k[1] - (0)*c[8]*k[0]*k[2] + (0)*c[8]*k[0] + (0)*c[8]*k[1]*k[1] + (0)*c[8]*k[1]*k[2] - (0)*c[8]*k[1] + (0)*c[8]*k[2]*k[2] - (0)*c[8]*k[2] - 4.00000000000001*c[8] - (0)*c[9]*k[0]*k[0] + (0)*c[9]*k[0]*k[1] - (0)*c[9]*k[0]*k[2] + (0)*c[9]*k[0] + (0)*c[9]*k[1]*k[1] + (0)*c[9]*k[1]*k[2] - (0)*c[9]*k[1] - (0)*c[9]*k[2]*k[2] + (0)*c[9]*k[2] - 4.0*c[9]",
            "(0)*c[0]*k[0]*k[0] - (0)*c[0]*k[0]*k[1] + (0)*c[0]*k[0]*k[2] - (0)*c[0]*k[0] - (0)*c[0]*k[1]*k[1] - (0)*c[0]*k[1]*k[2] + (0)*c[0]*k[1] + (0)*c[0]*k[2]*k[2] - (0)*c[0]*k[2] + 4.0*c[0] + (0)*c[1]*k[0]*k[0] + (0)*c[1]*k[0]*k[1] + (0)*c[1]*k[0]*k[2] - (0)*c[1]*k[0] - (0)*c[1]*k[1]*k[1] + (0)*c[1]*k[1]*k[2] - (0)*c[1]*k[1] + (0)*c[1]*k[2]*k[2] - (0)*c[1]*k[2] + (0)*c[1] - (0)*c[2]*k[0]*k[0] + (0)*c[2]*k[0]*k[1] - (0)*c[2]*k[0]*k[2] + (0)*c[2]*k[0] + (0)*c[2]*k[1]*k[1] + (0)*c[2]*k[1]*k[2] - (0)*c[2]*k[1] + (0)*c[2]*k[2]*k[2] + (0)*c[2]*k[2] - (0)*c[2] + (0)*c[3]*k[0]*k[0] - (0)*c[3]*k[0]*k[1] - (0)*c[3]*k[0]*k[2] + (0)*c[3]*k[0] - (0)*c[3]*k[1]*k[1] - (0)*c[3]*k[1]*k[2] + (0)*c[3]*k[1] - (0)*c[3]*k[2]*k[2] + (0)*c[3]*k[2] + (0)*c[3] - (0)*c[4]*k[0]*k[0] + (0)*c[4]*k[0]*k[1] + (0)*c[4]*k[0]*k[2] - (0)*c[4]*k[0] + (0)*c[4]*k[1]*k[1] + (0)*c[4]*k[1]*k[2] - (0)*c[4]*k[1] + (0)*c[4]*k[2]*k[2] - (0)*c[4]*k[2] - (0)*c[4] + (0)*c[5]*k[0]*k[0] - (0)*c[5]*k[0]*k[1] - (0)*c[5]*k[0]*k[2] + (0)*c[5]*k[0] - (0)*c[5]*k[1]*k[1] - (0)*c[5]*k[1]*k[2] + (0)*c[5]*k[1] - (0)*c[5]*k[2]*k[2] + (0)*c[5]*k[2] + 3.99999999999999*c[5] - (0)*c[6]*k[0]*k[0] + (0)*c[6]*k[0]*k[1] - (0)*c[6]*k[0]*k[2] + (0)*c[6]*k[0] + (0)*c[6]*k[1]*k[1] + (0)*c[6]*k[1]*k[2] - (0)*c[6]*k[1] + (0)*c[6]*k[2]*k[2] + (0)*c[6]*k[2] - (0)*c[6] - (0)*c[7]*k[0]*k[0] + (0)*c[7]*k[0]*k[1] + (0)*c[7]*k[0]*k[2] - (0)*c[7]*k[0] + (0)*c[7]*k[1]*k[1] + (0)*c[7]*k[1]*k[2] - (0)*c[7]*k[1] + (0)*c[7]*k[2]*k[2] - (0)*c[7]*k[2] - 3.99999999999999*c[7] + (0)*c[8]*k[0]*k[0] - (0)*c[8]*k[0]*k[1] + (0)*c[8]*k[0]*k[2] - (0)*c[8]*k[0] - (0)*c[8]*k[1]*k[1] - (0)*c[8]*k[1]*k[2] + (0)*c[8]*k[1] - (0)*c[8]*k[2]*k[2] - (0)*c[8]*k[2] + (0)*c[8] - (0)*c[9]*k[0]*k[0] + (0)*c[9]*k[0]*k[1] - (0)*c[9]*k[0]*k[2] + (0)*c[9]*k[0] + (0)*c[9]*k[1]*k[1] + (0)*c[9]*k[1]*k[2] - (0)*c[9]*k[1] - (0)*c[9]*k[2]*k[2] + (0)*c[9]*k[2] - 4.0*c[9]",
            "(0)*c[0]*k[0]*k[0] - (0)*c[0]*k[0]*k[1] + (0)*c[0]*k[0]*k[2] - (0)*c[0]*k[0] - (0)*c[0]*k[1]*k[1] - (0)*c[0]*k[1]*k[2] + (0)*c[0]*k[1] + (0)*c[0]*k[2]*k[2] - (0)*c[0]*k[2] + 4.0*c[0] - (0)*c[1]*k[0]*k[0] + (0)*c[1]*k[0]*k[1] + (0)*c[1]*k[0]*k[2] - (0)*c[1]*k[0] - (0)*c[1]*k[1]*k[1] + (0)*c[1]*k[1]*k[2] - (0)*c[1]*k[1] + (0)*c[1]*k[2]*k[2] - (0)*c[1]*k[2] + (0)*c[1] + (0)*c[2]*k[0]*k[0] - (0)*c[2]*k[0]*k[1] + (0)*c[2]*k[0]*k[2] - (0)*c[2]*k[0] - (0)*c[2]*k[1]*k[1] - (0)*c[2]*k[1]*k[2] + (0)*c[2]*k[1] - (0)*c[2]*k[2]*k[2] + (0)*c[2]*k[2] + (0)*c[2] - (0)*c[3]*k[0]*k[0] + (0)*c[3]*k[0]*k[1] - (0)*c[3]*k[0]*k[2] - (0)*c[3]*k[0] + (0)*c[3]*k[1]*k[1] + (0)*c[3]*k[1]*k[2] - (0)*c[3]*k[1] + (0)*c[3]*k[2]*k[2] - (0)*c[3]*k[2] - (0)*c[3] + (0)*c[4]*k[0]*k[0] - (0)*c[4]*k[0]*k[1] + (0)*c[4]*k[0]*k[2] + (0)*c[4]*k[0] - (0)*c[4]*k[1]*k[1] - (0)*c[4]*k[1]*k[2] + (0)*c[4]*k[1] - (0)*c[4]*k[2]*k[2] + (0)*c[4]*k[2] + (0)*c[4] - (0)*c[5]*k[0]*k[0] + (0)*c[5]*k[0]*k[1] + (0)*c[5]*k[0]*k[2] - (0)*c[5]*k[0] - (0)*c[5]*k[1]*k[1] + (0)*c[5]*k[1]*k[2] - (0)*c[5]*k[1] + (0)*c[5]*k[2]*k[2] - (0)*c[5]*k[2] + (0)*c[5] + (0)*c[6]*k[0]*k[0] - (0)*c[6]*k[0]*k[1] + (0)*c[6]*k[0]*k[2] - (0)*c[6]*k[0] - (0)*c[6]*k[1]*k[1] - (0)*c[6]*k[1]*k[2] + (0)*c[6]*k[1] - (0)*c[6]*k[2]*k[2] + (0)*c[6]*k[2] + 4.0*c[6] + (0)*c[7]*k[0]*k[0] - (0)*c[7]*k[0]*k[1] - (0)*c[7]*k[0]*k[2] + (0)*c[7]*k[0] + (0)*c[7]*k[1]*k[1] - (0)*c[7]*k[1]*k[2] + (0)*c[7]*k[1] - (0)*c[7]*k[2]*k[2] + (0)*c[7]*k[2] - (0)*c[7] - (0)*c[8]*k[0]*k[0] + (0)*c[8]*k[0]*k[1] - (0)*c[8]*k[0]*k[2] + (0)*c[8]*k[0] + (0)*c[8]*k[1]*k[1] + (0)*c[8]*k[1]*k[2] - (0)*c[8]*k[1] + (0)*c[8]*k[2]*k[2] - (0)*c[8]*k[2] - 4.00000000000001*c[8] - (0)*c[9]*k[0]*k[0] + (0)*c[9]*k[0]*k[1] - (0)*c[9]*k[0]*k[2] + (0)*c[9]*k[0] + (0)*c[9]*k[1]*k[1] + (0)*c[9]*k[1]*k[2] - (0)*c[9]*k[1] - (0)*c[9]*k[2]*k[2] + (0)*c[9]*k[2] - 4.0*c[9]",
            "(0)*c[0]*k[0]*k[0] - (0)*c[0]*k[0]*k[1] + (0)*c[0]*k[0]*k[2] - (0)*c[0]*k[0] - (0)*c[0]*k[1]*k[1] - (0)*c[0]*k[1]*k[2] + (0)*c[0]*k[1] + (0)*c[0]*k[2]*k[2] - (0)*c[0]*k[2] + 4.0*c[0] - (0)*c[1]*k[0]*k[0] + (0)*c[1]*k[0]*k[1] - (0)*c[1]*k[0]*k[2] + (0)*c[1]*k[0] + (0)*c[1]*k[1]*k[1] + (0)*c[1]*k[1]*k[2] + (0)*c[1]*k[1] - (0)*c[1]*k[2]*k[2] + (0)*c[1]*k[2] - (0)*c[1] + (0)*c[2]*k[0]*k[0] - (0)*c[2]*k[0]*k[1] + (0)*c[2]*k[0]*k[2] - (0)*c[2]*k[0] - (0)*c[2]*k[1]*k[1] - (0)*c[2]*k[1]*k[2] + (0)*c[2]*k[1] - (0)*c[2]*k[2]*k[2] + (0)*c[2]*k[2] + 3.99999999999999*c[2] + (0)*c[3]*k[0]*k[0] - (0)*c[3]*k[0]*k[1] - (0)*c[3]*k[0]*k[2] + (0)*c[3]*k[0] + (0)*c[3]*k[1]*k[1] - (0)*c[3]*k[1]*k[2] + (0)*c[3]*k[1] - (0)*c[3]*k[2]*k[2] + (0)*c[3]*k[2] - (0)*c[3] + (0)*c[4]*k[0]*k[0] + (0)*c[4]*k[0]*k[1] + (0)*c[4]*k[0]*k[2] - (0)*c[4]*k[0] + (0)*c[4]*k[1]*k[1] + (0)*c[4]*k[1]*k[2] - (0)*c[4]*k[1] + (0)*c[4]*k[2]*k[2] - (0)*c[4]*k[2] + (0)*c[4] - (0)*c[5]*k[0]*k[0] - (0)*c[5]*k[0]*k[1] - (0)*c[5]*k[0]*k[2] + (0)*c[5]*k[0] - (0)*c[5]*k[1]*k[1] + (0)*c[5]*k[1]*k[2] - (0)*c[5]*k[1] + (0)*c[5]*k[2]*k[2] + (0)*c[5]*k[2] - (0)*c[5] - (0)*c[6]*k[0]*k[0] + (0)*c[6]*k[0]*k[1] + (0)*c[6]*k[0]*k[2] - (0)*c[6]*k[0] - (0)*c[6]*k[1]*k[1] + (0)*c[6]*k[1]*k[2] - (0)*c[6]*k[1] + (0)*c[6]*k[2]*k[2] - (0)*c[6]*k[2] + (0)*c[6] - (0)*c[7]*k[0]*k[0] - (0)*c[7]*k[0]*k[1] - (0)*c[7]*k[0]*k[2] + (0)*c[7]*k[0] - (0)*c[7]*k[1]*k[1] - (0)*c[7]*k[1]*k[2] + (0)*c[7]*k[1] - (0)*c[7]*k[2]*k[2] + (0)*c[7]*k[2] - (0)*c[7] - (0)*c[8]*k[0]*k[0] + (0)*c[8]*k[0]*k[1] - (0)*c[8]*k[0]*k[2] + (0)*c[8]*k[0] + (0)*c[8]*k[1]*k[1] + (0)*c[8]*k[1]*k[2] - (0)*c[8]*k[1] + (0)*c[8]*k[2]*k[2] - (0)*c[8]*k[2] - 8.0*c[8] + (0)*c[9]*k[0]*k[0] - (0)*c[9]*k[0]*k[1] - (0)*c[9]*k[0]*k[2] + (0)*c[9]*k[0] + (0)*c[9]*k[1]*k[1] - (0)*c[9]*k[1]*k[2] + (0)*c[9]*k[1] - (0)*c[9]*k[2]*k[2] + (0)*c[9]*k[2] - (0)*c[9]",
            "(0)*c[0]*k[0]*k[0] - (0)*c[0]*k[0]*k[1] + (0)*c[0]*k[0]*k[2] - (0)*c[0]*k[0] - (0)*c[0]*k[1]*k[1] - (0)*c[0]*k[1]*k[2] + (0)*c[0]*k[1] + (0)*c[0]*k[2]*k[2] - (0)*c[0]*k[2] + 4.0*c[0] + (0)*c[1]*k[0]*k[0] - (0)*c[1]*k[0]*k[1] - (0)*c[1]*k[0]*k[2] + (0)*c[1]*k[0] - (0)*c[1]*k[1]*k[1] - (0)*c[1]*k[1]*k[2] + (0)*c[1]*k[1] - (0)*c[1]*k[2]*k[2] + (0)*c[1]*k[2] - (0)*c[1] - (0)*c[2]*k[0]*k[0] + (0)*c[2]*k[0]*k[1] - (0)*c[2]*k[0]*k[2] + (0)*c[2]*k[0] + (0)*c[2]*k[1]*k[1] + (0)*c[2]*k[1]*k[2] - (0)*c[2]*k[1] + (0)*c[2]*k[2]*k[2] - (0)*c[2]*k[2] + (0)*c[2] - (0)*c[3]*k[0]*k[0] + (0)*c[3]*k[0]*k[1] + (0)*c[3]*k[0]*k[2] - (0)*c[3]*k[0] + (0)*c[3]*k[1]*k[1] + (0)*c[3]*k[1]*k[2] - (0)*c[3]*k[1] + (0)*c[3]*k[2]*k[2] + (0)*c[3]*k[2] - (0)*c[3] + (0)*c[4]*k[0]*k[0] - (0)*c[4]*k[0]*k[1] - (0)*c[4]*k[0]*k[2] + (0)*c[4]*k[0] - (0)*c[4]*k[1]*k[1] - (0)*c[4]*k[1]*k[2] + (0)*c[4]*k[1] - (0)*c[4]*k[2]*k[2] + (0)*c[4]*k[2] + 4.0*c[4] + (0)*c[5]*k[0]*k[0] + (0)*c[5]*k[0]*k[1] + (0)*c[5]*k[0]*k[2] + (0)*c[5]*k[0] + (0)*c[5]*k[1]*k[1] + (0)*c[5]*k[1]*k[2] + (0)*c[5]*k[1] - (0)*c[5]*k[2]*k[2] + (0)*c[5]*k[2] - (0)*c[5] + (0)*c[6]*k[0]*k[0] + (0)*c[6]*k[0]*k[1] + (0)*c[6]*k[0]*k[2] - (0)*c[6]*k[0] - (0)*c[6]*k[1]*k[1] + (0)*c[6]*k[1]*k[2] - (0)*c[6]*k[1] + (0)*c[6]*k[2]*k[2] - (0)*c[6]*k[2] - (0)*c[6] - (0)*c[7]*k[0]*k[0] + (0)*c[7]*k[0]*k[1] + (0)*c[7]*k[0]*k[2] - (0)*c[7]*k[0] + (0)*c[7]*k[1]*k[1] + (0)*c[7]*k[1]*k[2] - (0)*c[7]*k[1] + (0)*c[7]*k[2]*k[2] - (0)*c[7]*k[2] - 3.99999999999999*c[7] - (0)*c[8]*k[0]*k[0] + (0)*c[8]*k[0]*k[1] - (0)*c[8]*k[0]*k[2] + (0)*c[8]*k[0] + (0)*c[8]*k[1]*k[1] + (0)*c[8]*k[1]*k[2] - (0)*c[8]*k[1] - (0)*c[8]*k[2]*k[2] + (0)*c[8]*k[2] - 4.0*c[8] - (0)*c[9]*k[0]*k[0] - (0)*c[9]*k[0]*k[1] - (0)*c[9]*k[0]*k[2] + (0)*c[9]*k[0] + (0)*c[9]*k[1]*k[1] - (0)*c[9]*k[1]*k[2] + (0)*c[9]*k[1] - (0)*c[9]*k[2]*k[2] + (0)*c[9]*k[2] - (0)*c[9]",
            "(0)*c[0]*k[0]*k[0] - (0)*c[0]*k[0]*k[1] + (0)*c[0]*k[0]*k[2] - (0)*c[0]*k[0] - (0)*c[0]*k[1]*k[1] - (0)*c[0]*k[1]*k[2] + (0)*c[0]*k[1] + (0)*c[0]*k[2]*k[2] - (0)*c[0]*k[2] + 4.0*c[0] + (0)*c[1]*k[0]*k[0] + (0)*c[1]*k[0]*k[1] + (0)*c[1]*k[0]*k[2] - (0)*c[1]*k[0] - (0)*c[1]*k[1]*k[1] + (0)*c[1]*k[1]*k[2] - (0)*c[1]*k[1] + (0)*c[1]*k[2]*k[2] - (0)*c[1]*k[2] + (0)*c[1] - (0)*c[2]*k[0]*k[0] + (0)*c[2]*k[0]*k[1] - (0)*c[2]*k[0]*k[2] + (0)*c[2]*k[0] + (0)*c[2]*k[1]*k[1] + (0)*c[2]*k[1]*k[2] - (0)*c[2]*k[1] + (0)*c[2]*k[2]*k[2] + (0)*c[2]*k[2] - (0)*c[2] + (0)*c[3]*k[0]*k[0] - (0)*c[3]*k[0]*k[1] - (0)*c[3]*k[0]*k[2] + (0)*c[3]*k[0] - (0)*c[3]*k[1]*k[1] - (0)*c[3]*k[1]*k[2] + (0)*c[3]*k[1] - (0)*c[3]*k[2]*k[2] + (0)*c[3]*k[2] + (0)*c[3] - (0)*c[4]*k[0]*k[0] + (0)*c[4]*k[0]*k[1] + (0)*c[4]*k[0]*k[2] - (0)*c[4]*k[0] + (0)*c[4]*k[1]*k[1] + (0)*c[4]*k[1]*k[2] - (0)*c[4]*k[1] + (0)*c[4]*k[2]*k[2] - (0)*c[4]*k[2] - (0)*c[4] + (0)*c[5]*k[0]*k[0] - (0)*c[5]*k[0]*k[1] - (0)*c[5]*k[0]*k[2] + (0)*c[5]*k[0] - (0)*c[5]*k[1]*k[1] - (0)*c[5]*k[1]*k[2] + (0)*c[5]*k[1] - (0)*c[5]*k[2]*k[2] + (0)*c[5]*k[2] + 3.99999999999999*c[5] - (0)*c[6]*k[0]*k[0] + (0)*c[6]*k[0]*k[1] - (0)*c[6]*k[0]*k[2] + (0)*c[6]*k[0] + (0)*c[6]*k[1]*k[1] + (0)*c[6]*k[1]*k[2] - (0)*c[6]*k[1] + (0)*c[6]*k[2]*k[2] + (0)*c[6]*k[2] - (0)*c[6] - (0)*c[7]*k[0]*k[0] + (0)*c[7]*k[0]*k[1] + (0)*c[7]*k[0]*k[2] - (0)*c[7]*k[0] + (0)*c[7]*k[1]*k[1] + (0)*c[7]*k[1]*k[2] - (0)*c[7]*k[1] + (0)*c[7]*k[2]*k[2] - (0)*c[7]*k[2] - 3.99999999999999*c[7] + (0)*c[8]*k[0]*k[0] - (0)*c[8]*k[0]*k[1] + (0)*c[8]*k[0]*k[2] - (0)*c[8]*k[0] - (0)*c[8]*k[1]*k[1] - (0)*c[8]*k[1]*k[2] + (0)*c[8]*k[1] - (0)*c[8]*k[2]*k[2] - (0)*c[8]*k[2] + (0)*c[8] - (0)*c[9]*k[0]*k[0] + (0)*c[9]*k[0]*k[1] - (0)*c[9]*k[0]*k[2] + (0)*c[9]*k[0] + (0)*c[9]*k[1]*k[1] + (0)*c[9]*k[1]*k[2] - (0)*c[9]*k[1] - (0)*c[9]*k[2]*k[2] + (0)*c[9]*k[2] - 4.0*c[9]",
            "(0)*c[0]*k[0]*k[0] - (0)*c[0]*k[0]*k[1] + (0)*c[0]*k[0]*k[2] - (0)*c[0]*k[0] - (0)*c[0]*k[1]*k[1] - (0)*c[0]*k[1]*k[2] + (0)*c[0]*k[1] + (0)*c[0]*k[2]*k[2] - (0)*c[0]*k[2] + 4.0*c[0] + (0)*c[1]*k[0]*k[0] - (0)*c[1]*k[0]*k[1] - (0)*c[1]*k[0]*k[2] + (0)*c[1]*k[0] - (0)*c[1]*k[1]*k[1] - (0)*c[1]*k[1]*k[2] + (0)*c[1]*k[1] - (0)*c[1]*k[2]*k[2] + (0)*c[1]*k[2] - (0)*c[1] - (0)*c[2]*k[0]*k[0] + (0)*c[2]*k[0]*k[1] - (0)*c[2]*k[0]*k[2] + (0)*c[2]*k[0] + (0)*c[2]*k[1]*k[1] + (0)*c[2]*k[1]*k[2] - (0)*c[2]*k[1] + (0)*c[2]*k[2]*k[2] - (0)*c[2]*k[2] + (0)*c[2] - (0)*c[3]*k[0]*k[0] + (0)*c[3]*k[0]*k[1] + (0)*c[3]*k[0]*k[2] - (0)*c[3]*k[0] + (0)*c[3]*k[1]*k[1] + (0)*c[3]*k[1]*k[2] - (0)*c[3]*k[1] + (0)*c[3]*k[2]*k[2] + (0)*c[3]*k[2] - (0)*c[3] + (0)*c[4]*k[0]*k[0] - (0)*c[4]*k[0]*k[1] - (0)*c[4]*k[0]*k[2] + (0)*c[4]*k[0] - (0)*c[4]*k[1]*k[1] - (0)*c[4]*k[1]*k[2] + (0)*c[4]*k[1] - (0)*c[4]*k[2]*k[2] + (0)*c[4]*k[2] + 4.0*c[4] + (0)*c[5]*k[0]*k[0] + (0)*c[5]*k[0]*k[1] + (0)*c[5]*k[0]*k[2] + (0)*c[5]*k[0] + (0)*c[5]*k[1]*k[1] + (0)*c[5]*k[1]*k[2] + (0)*c[5]*k[1] - (0)*c[5]*k[2]*k[2] + (0)*c[5]*k[2] - (0)*c[5] + (0)*c[6]*k[0]*k[0] + (0)*c[6]*k[0]*k[1] + (0)*c[6]*k[0]*k[2] - (0)*c[6]*k[0] - (0)*c[6]*k[1]*k[1] + (0)*c[6]*k[1]*k[2] - (0)*c[6]*k[1] + (0)*c[6]*k[2]*k[2] - (0)*c[6]*k[2] - (0)*c[6] - (0)*c[7]*k[0]*k[0] + (0)*c[7]*k[0]*k[1] + (0)*c[7]*k[0]*k[2] - (0)*c[7]*k[0] + (0)*c[7]*k[1]*k[1] + (0)*c[7]*k[1]*k[2] - (0)*c[7]*k[1] + (0)*c[7]*k[2]*k[2] - (0)*c[7]*k[2] - 3.99999999999999*c[7] - (0)*c[8]*k[0]*k[0] + (0)*c[8]*k[0]*k[1] - (0)*c[8]*k[0]*k[2] + (0)*c[8]*k[0] + (0)*c[8]*k[1]*k[1] + (0)*c[8]*k[1]*k[2] - (0)*c[8]*k[1] - (0)*c[8]*k[2]*k[2] + (0)*c[8]*k[2] - 4.0*c[8] - (0)*c[9]*k[0]*k[0] - (0)*c[9]*k[0]*k[1] - (0)*c[9]*k[0]*k[2] + (0)*c[9]*k[0] + (0)*c[9]*k[1]*k[1] - (0)*c[9]*k[1]*k[2] + (0)*c[9]*k[1] - (0)*c[9]*k[2]*k[2] + (0)*c[9]*k[2] - (0)*c[9]",
            "(0)*c[0]*k[0]*k[0] - (0)*c[0]*k[0]*k[1] + (0)*c[0]*k[0]*k[2] - (0)*c[0]*k[0] - (0)*c[0]*k[1]*k[1] - (0)*c[0]*k[1]*k[2] + (0)*c[0]*k[1] + (0)*c[0]*k[2]*k[2] - (0)*c[0]*k[2] + 4.0*c[0] + (0)*c[1]*k[0]*k[0] + (0)*c[1]*k[0]*k[1] - (0)*c[1]*k[0]*k[2] + (0)*c[1]*k[0] + (0)*c[1]*k[1]*k[1] + (0)*c[1]*k[1]*k[2] + (0)*c[1]*k[1] + (0)*c[1]*k[2]*k[2] + (0)*c[1]*k[2] - (0)*c[1] - (0)*c[2]*k[0]*k[0] - (0)*c[2]*k[0]*k[1] - (0)*c[2]*k[0]*k[2] - (0)*c[2]*k[0] - (0)*c[2]*k[1]*k[1] - (0)*c[2]*k[1]*k[2] + (0)*c[2]*k[1] - (0)*c[2]*k[2]*k[2] - (0)*c[2]*k[2] + (0)*c[2] + (0)*c[3]*k[0]*k[0] - (0)*c[3]*k[0]*k[1] - (0)*c[3]*k[0]*k[2] + (0)*c[3]*k[0] - (0)*c[3]*k[1]*k[1] - (0)*c[3]*k[1]*k[2] + (0)*c[3]*k[1] - (0)*c[3]*k[2]*k[2] + (0)*c[3]*k[2] + 4.0*c[3] - (0)*c[4]*k[0]*k[0] + (0)*c[4]*k[0]*k[1] - (0)*c[4]*k[0]*k[2] - (0)*c[4]*k[0] + (0)*c[4]*k[1]*k[1] + (0)*c[4]*k[1]*k[2] - (0)*c[4]*k[1] + (0)*c[4]*k[2]*k[2] + (0)*c[4]*k[2] - (0)*c[4] + (0)*c[5]*k[0]*k[0] + (0)*c[5]*k[0]*k[1] + (0)*c[5]*k[0]*k[2] - (0)*c[5]*k[0] - (0)*c[5]*k[1]*k[1] + (0)*c[5]*k[1]*k[2] - (0)*c[5]*k[1] + (0)*c[5]*k[2]*k[2] - (0)*c[5]*k[2] + (0)*c[5] + (0)*c[6]*k[0]*k[0] - (0)*c[6]*k[0]*k[1] - (0)*c[6]*k[0]*k[2] + (0)*c[6]*k[0] - (0)*c[6]*k[1]*k[1] - (0)*c[6]*k[1]*k[2] - (0)*c[6]*k[1] - (0)*c[6]*k[2]*k[2] + (0)*c[6]*k[2] - (0)*c[6] - (0)*c[7]*k[0]*k[0] + (0)*c[7]*k[0]*k[1] - (0)*c[7]*k[0]*k[2] - (0)*c[7]*k[0] + (0)*c[7]*k[1]*k[1] + (0)*c[7]*k[1]*k[2] - (0)*c[7]*k[1] + (0)*c[7]*k[2]*k[2] - (0)*c[7]*k[2] - 7.99999999999999*c[7] + (0)*c[8]*k[0]*k[0] - (0)*c[8]*k[0]*k[1] + (0)*c[8]*k[0]*k[2] + (0)*c[8]*k[0] - (0)*c[8]*k[1]*k[1] - (0)*c[8]*k[1]*k[2] + (0)*c[8]*k[1] - (0)*c[8]*k[2]*k[2] - (0)*c[8]*k[2] + (0)*c[8] - (0)*c[9]*k[0]*k[0] - (0)*c[9]*k[0]*k[1] - (0)*c[9]*k[0]*k[2] + (0)*c[9]*k[0] + (0)*c[9]*k[1]*k[1] - (0)*c[9]*k[1]*k[2] + (0)*c[9]*k[1] - (0)*c[9]*k[2]*k[2] + (0)*c[9]*k[2] - (0)*c[9]"
        ]
    },
    "k": [
        0.25,
        0.25,
        0.25
    ],
    "isAffine": true,
    "degree": 2,
    "dim": 3,
    "s_basis_functions": [
        "2.0*k[0]*k[0] + 4.0*k[0]*k[1] + 4.0*k[0]*k[2] - 3.0*k[0] + 2.0*k[1]*k[1] + 4.0*k[1]*k[2] - 3.0*k[1] + 2.0*k[2]*k[2] - 3.0*k[2] + 1.0",
        "2.0*k[0]*k[0] - (0)*k[0]*k[1] - (0)*k[0]*k[2] - 1.0*k[0] - (0)*k[1]*k[1] + (0)*k[1] + (0)*k[2]*k[2] - (0)*k[2] + (0)",
        "(0)*k[0]*k[0] + (0)*k[0]*k[1] - (0)*k[0]*k[2] + (0)*k[0] + 2.0*k[1]*k[1] - (0)*k[1]*k[2] - 1.0*k[1]",
        "(0)*k[0]*k[0] - (0)*k[0]*k[1] + (0)*k[0]*k[2] + (0)*k[0] - (0)*k[1]*k[1] - (0)*k[1]*k[2] + (0)*k[1] + 2.0*k[2]*k[2] - 1.0*k[2] - (0)",
        "(0)*k[0]*k[0] + (0)*k[0]*k[1] - (0)*k[0]*k[2] - (0)*k[0] + (0)*k[1]*k[1] + 4.0*k[1]*k[2] - (0)*k[1] - (0)*k[2]*k[2] + (0)",
        "(0)*k[0]*k[0] + (0)*k[0]*k[1] + 4.0*k[0]*k[2] + (0)*k[0] - (0)*k[1]*k[1] - (0)*k[1]*k[2] + (0)*k[1] + (0)*k[2]*k[2] - (0)*k[2] - (0)",
        "(0)*k[0]*k[0] + 4.0*k[0]*k[1] + (0)*k[0]*k[2] + (0)*k[0] + (0)*k[1]*k[1] + (0)*k[1]*k[2] - (0)*k[1] + (0)*k[2]*k[2] - (0)*k[2] + (0)",
        "(0)*k[0]*k[0] - (0)*k[0]*k[1] - 4.0*k[0]*k[2] - (0)*k[0] + (0)*k[1]*k[1] - 4.0*k[1]*k[2] - (0)*k[1] - 4.0*k[2]*k[2] + 4.0*k[2] + (0)",
        "(0)*k[0]*k[0] - 4.0*k[0]*k[1] - (0)*k[0]*k[2] - 4.0*k[1]*k[1] - 4.0*k[1]*k[2] + 4.0*k[1] - (0)*k[2] - (0)",
        "-4.0*k[0]*k[0] - 4.0*k[0]*k[1] - 4.0*k[0]*k[2] + 4.0*k[0] - (0)*k[1]*k[2] + (0)*k[1] - (0)*k[2]*k[2] + (0)*k[2] - (0)"
    ],
    "test": "(newpos[0] + 1.0e-14 >= 0) && (newpos[1] + 1.0e-14 >= 0) && (newpos[2] + 1.0e-14 >= 0) && (newpos[0] + newpos[1] + newpos[2] - 1.0e-14 <= 1)",
    "gdim": 4,
    "g_basis_functions": [
        "-1.0*k[0] - 1.0*k[1] - 1.0*k[2] + 1.0",
        "1.0*k[0]",
        "1.0*k[1] - (0)",
        "1.0*k[2]"
    ]
}